Workbook

Sheet README
A1: T5-6 · 표 5-6. GPT-5.4-mini의 정보조건별 정책가치(Oracle-α)
A2: 논문 인쇄값을 계산 입력으로 쓰지 않고, 선택 실행의 실제 산출물에서 값을 계산한 Excel입니다.
A4: 항목 | B4: 내용
A5: 선택 실행 | B5: V11_FINAL_FROZEN_REPLAY_RESUME
A6: 실행 방식 | B6: FrozenReplay
A7: 논문 항목 읽기 | B7: 논문 DOCX에서 번호·제목·위치만 동적으로 읽음
A8: 논문 위치 | B8: 5.4 정보조건과 기업명 인식 · 인쇄면 60
A9: 관측·집계 단위 | B9: source_file + policy
A10: 선택 조건 | B10: [[{"column": "policy", "op": "in", "values": ["C4", "C6"]}]]
A11: 계산 방법 | B11: 같은 기업의 행동 후 Oracle 점수에서 그 기업의 무행동 Oracle 점수를 뺀 뒤 기업 단위로 집계
A12: 생산 코드 | B12: src/credit_recourse/analysis/n5_budget_frontier_holm_inference.py
A13: 실제 입력 산출물 | B13: frozen_outputs/analysis/paper_repro/03_output_contract_diagnostics/n5_generation_budget_frontier_holm/n5_budget_frontier_table_patch.csv frozen_outputs/final_freeze/llm_runs/N5_C6_L1_1p27_ICa_gpt54mini_p50_main_seed1_20260707/stage8_llm_multi_oracle_eval/llm_stage8_multi_oracle_scores.parquet frozen_outputs/final_freeze/llm_runs/N5_C6_L1_1p27_ICb_gpt54mini_p50_main_seed1_20260707/stage8_llm_multi_oracle_eval/llm_stage8_multi_oracle_scores.parquet frozen_outputs/final_freeze/llm_runs/N5_C6_L1_1p27_ICc_gpt54mini_p50_main_seed1_20260707/stage8_llm_multi_oracle_eval/llm_stage8_multi_oracle_scores.parquet frozen_outputs/final_freeze/llm_runs/N5_C6_L1_1p27_ICa_gpt54mini_p50_main_seed1_20260707/stage8_llm_multi_oracle_eval/llm_stage8_policy_summary.csv frozen_outputs/final_freeze/llm_runs/N5_C6_L1_1p27_ICb_gpt54mini_p50_main_seed1_20260707/stage8_llm_multi_oracle_eval/llm_stage8_policy_summary.csv frozen_outputs/final_freeze/llm_runs/N5_C6_L1_1p27_ICc_gpt54mini_p50_main_seed1_20260707/stage8_llm_multi_oracle_eval/llm_stage8_policy_summary.csv

Sheet SOURCE
A1: T5-6 · 실제 입력 산출물
A2: 선택 실행에서 읽은 실제 중간·최종 산출물입니다. 아래 ANALYSIS가 이 셀들을 직접 참조합니다.
A4: 입력 1: frozen_outputs/analysis/paper_repro/03_output_contract_diagnostics/n5_generation_budget_frontier_holm/n5_budget_frontier_table_patch.csv
A5: 파일 크기(bytes) | B5: 1314 | C5: 생산 코드 | D5: src/credit_recourse/analysis/n5_budget_frontier_holm_inference.py | E5: SHA256 | F5: 2EA25F0676901FC49917066769CDD23659B0AD2C60FFB59A6ECCD6E3700C654D | G5: 읽기 상태 | H5: OK
A6: design | B6: oracle_backend | C6: budget_label | D6: l1_budget | E6: run_label | F6: n_pairs | G6: mean_C4 | H6: mean_C6 | I6: mean_C6_minus_C4 | J6: C6_minus_C4_p_holm | K6: C6_minus_C4_sig | L6: C6_minus_unbounded_gap | M6: C6_minus_unbounded_p_holm | N6: C6_minus_unbounded_sig | O6: interaction_or_package_DID_gap | P6: interaction_or_package_DID_p_holm | Q6: interaction_or_package_DID_sig
A7: legacy_c6_only | B7: alpha | C7: 0p75 | D7: 0.75 | E7: N5F_C4C6_L1_0p75_ICb_gpt54mini_p50_main_seed1_20260712_083213 | F7: 575 | G7: 0.84806938 | H7: 0.84954939 | I7: 0.0014800074 | J7: 0.22535094 | K7: n.s. | L7: -0.20934534 | M7: 5.7373954e-13 | N7: *** | O7: -0.18567208 | P7: 2.6114801e-07 | Q7: ***
A8: legacy_c6_only | B8: alpha | C8: 1p27 | D8: 1.27 | E8: N5F_C4C6_L1_1p27_ICb_gpt54mini_p50_main_seed1_20260712_083213 | F8: 575 | G8: 0.82994709 | H8: 0.9114068 | I8: 0.081459712 | J8: 0.03275921 | K8: * | L8: -0.14748793 | M8: 5.283671e-07 | N8: *** | O8: -0.10569237 | P8: 0.0010040514 | Q8: **
A9: legacy_c6_only | B9: alpha | C9: 2p00 | D9: 2 | E9: N5F_C4C6_L1_2p00_ICb_gpt54mini_p50_main_seed1_20260712_083213 | F9: 575 | G9: 0.89564649 | H9: 1.069689 | I9: 0.17404248 | J9: 1.0682402e-07 | K9: *** | L9: 0.010794236 | M9: 0.77426926 | N9: n.s. | O9: -0.013109608 | P9: 0.4786527 | Q9: n.s.
A10: legacy_c6_only | B10: alpha | C10: unbounded | E10: N5F_C4C6_L1_unbounded_ICb_gpt54mini_p50_main_seed1_20260712_083213 | F10: 575 | G10: 0.87174264 | H10: 1.0588947 | I10: 0.18715208 | J10: 3.2477506e-11 | K10: ***
A13: 입력 2: frozen_outputs/final_freeze/llm_runs/N5_C6_L1_1p27_ICa_gpt54mini_p50_main_seed1_20260707/stage8_llm_multi_oracle_eval/llm_stage8_multi_oracle_scores.parquet
A14: 파일 크기(bytes) | B14: 75450 | C14: 생산 코드 | D14: src/credit_recourse/analysis/n5_budget_frontier_holm_inference.py | E14: SHA256 | F14: 8CA3186823E010D031F8A0005EDB4896AE2909ABE43D965DA5D130B49868FE52 | G14: 읽기 상태 | H14: TRUNCATED
A15: row_id | B15: policy | C15: mode | D15: candidate_id | E15: R_score_alpha | F15: R_score_beta | G15: R_score_gamma | H15: noop_R_score_alpha | I15: delta_R_score_alpha | J15: noop_R_score_beta | K15: delta_R_score_beta | L15: noop_R_score_gamma | M15: delta_R_score_gamma
A16: 0 | B16: C4 | C16: free_form_10d | D16: DL1_deleverage_mild | E16: 80.762481 | F16: 71.661882 | G16: 76.170598 | H16: 80.762481 | I16: 0 | J16: 71.550825 | K16: 0.11105726 | L16: 75.110398 | M16: 1.0602005
A17: 0 | B17: C6 | C17: free_form_10d | D17: DL1_deleverage_mild | E17: 80.762481 | F17: 71.661882 | G17: 76.170598 | H17: 80.762481 | I17: 0 | J17: 71.550825 | K17: 0.11105726 | L17: 75.110398 | M17: 1.0602005
A18: 1 | B18: C4 | C18: free_form_10d | D18: OE1_cost_efficiency_mild | E18: 77.977741 | F18: 76.194731 | G18: 78.841487 | H18: 77.977741 | I18: 0 | J18: 76.119154 | K18: 0.075577392 | L18: 78.841487 | M18: 0
A19: 1 | B19: C6 | C19: free_form_10d | D19: OE1_cost_efficiency_mild | E19: 77.977741 | F19: 76.194731 | G19: 78.841487 | H19: 77.977741 | I19: 0 | J19: 76.119154 | K19: 0.075577392 | L19: 78.841487 | M19: 0
A20: 2 | B20: C4 | C20: free_form_10d | D20: OE1_cost_efficiency_mild | E20: 69.166072 | F20: 67.384023 | G20: 69.936775 | H20: 68.2742 | I20: 0.89187138 | J20: 67.243536 | K20: 0.14048718 | L20: 69.936775 | M20: 0
A21: 2 | B21: C6 | C21: free_form_10d | D21: OE2_cost_efficiency_moderate | E21: 69.44826 | F21: 67.443398 | G21: 69.936775 | H21: 68.2742 | I21: 1.1740594 | J21: 67.243536 | K21: 0.19986187 | L21: 69.936775 | M21: 0
A22: 3 | B22: C4 | C22: free_form_10d | D22: MX1_cost_and_deleverage | E22: 72.172397 | F22: 68.447831 | G22: 78.124746 | H22: 70.998337 | I22: 1.1740594 | J22: 68.290359 | K22: 0.15747156 | L22: 77.628703 | M22: 0.49604281
A23: 3 | B23: C6 | C23: free_form_10d | D23: OE2_cost_efficiency_moderate | E23: 72.172397 | F23: 68.485544 | G23: 78.124746 | H23: 70.998337 | I23: 1.1740594 | J23: 68.290359 | K23: 0.19518445 | L23: 77.628703 | M23: 0.49604281
A24: 4 | B24: C4 | C24: free_form_10d | D24: OE1_cost_efficiency_mild | E24: 77.201711 | F24: 75.859954 | G24: 70.40531 | H24: 75.0503 | I24: 2.1514108 | J24: 75.813074 | K24: 0.046879229 | L24: 69.89615 | M24: 0.50916032
A25: 4 | B25: C6 | C25: free_form_10d | D25: OE2_cost_efficiency_moderate | E25: 77.201711 | F25: 75.887708 | G25: 70.40531 | H25: 75.0503 | I25: 2.1514108 | J25: 75.813074 | K25: 0.07463403 | L25: 69.89615 | M25: 0.50916032
A26: 5 | B26: C4 | C26: free_form_10d | D26: OE2_cost_efficiency_moderate | E26: 70.936712 | F26: 68.200615 | G26: 70.814909 | H26: 70.747307 | I26: 0.18940416 | J26: 68.17692 | K26: 0.023695234 | L26: 70.814909 | M26: 0
A27: 5 | B27: C6 | C27: free_form_10d | D27: OE1_cost_efficiency_mild | E27: 70.936712 | F27: 68.198817 | G27: 70.814909 | H27: 70.747307 | I27: 0.18940416 | J27: 68.17692 | K27: 0.021897008 | L27: 70.814909 | M27: 0
... A265: 124 | B265: C6 | C265: free_form_10d | D265: OE2_cost_efficiency_moderate | E265: 83.176164 | F265: 73.513016 | G265: 82.578839 | H265: 80.092817 | I265: 3.0833473 | J265: 73.260612 | K265: 0.25240393 | L265: 80.443514 | M265: 2.1353258
A268: 입력 3: frozen_outputs/final_freeze/llm_runs/N5_C6_L1_1p27_ICb_gpt54mini_p50_main_seed1_20260707/stage8_llm_multi_oracle_eval/llm_stage8_multi_oracle_scores.parquet
A269: 파일 크기(bytes) | B269: 75366 | C269: 생산 코드 | D269: src/credit_recourse/analysis/n5_budget_frontier_holm_inference.py | E269: SHA256 | F269: 3BBB0EB7EF7DB1B9876B94A0A4C0D30C0636FA7A7A95760D318D57DD3183A8FA | G269: 읽기 상태 | H269: TRUNCATED
A270: row_id | B270: policy | C270: mode | D270: candidate_id | E270: R_score_alpha | F270: R_score_beta | G270: R_score_gamma | H270: noop_R_score_alpha | I270: delta_R_score_alpha | J270: noop_R_score_beta | K270: delta_R_score_beta | L270: noop_R_score_gamma | M270: delta_R_score_gamma
A271: 0 | B271: C4 | C271: free_form_10d | D271: MX1_cost_and_deleverage | E271: 80.762481 | F271: 71.645509 | G271: 75.487351 | H271: 80.762481 | I271: 0 | J271: 71.550825 | K271: 0.094684155 | L271: 75.110398 | M271: 0.37695357
A272: 0 | B272: C6 | C272: free_form_10d | D272: MX1_cost_and_deleverage | E272: 80.762481 | F272: 71.645509 | G272: 75.487351 | H272: 80.762481 | I272: 0 | J272: 71.550825 | K272: 0.094684155 | L272: 75.110398 | M272: 0.37695357
A273: 1 | B273: C4 | C273: free_form_10d | D273: DL1_deleverage_mild | E273: 82.740507 | F273: 76.263202 | G273: 79.076382 | H273: 77.977741 | I273: 4.7627666 | J273: 76.119154 | K273: 0.14404767 | L273: 78.841487 | M273: 0.23489484
A274: 1 | B274: C6 | C274: free_form_10d | D274: OE1_cost_efficiency_mild | E274: 82.740507 | F274: 76.235078 | G274: 78.760402 | H274: 77.977741 | I274: 4.7627666 | J274: 76.119154 | K274: 0.11592349 | L274: 78.841487 | M274: -0.08108462
A275: 2 | B275: C4 | C275: free_form_10d | D275: OE2_cost_efficiency_moderate | E275: 68.2742 | F275: 67.369476 | G275: 69.936775 | H275: 68.2742 | I275: 0 | J275: 67.243536 | K275: 0.12593987 | L275: 69.936775 | M275: 0
A276: 2 | B276: C6 | C276: free_form_10d | D276: OE2_cost_efficiency_moderate | E276: 69.44826 | F276: 67.414209 | G276: 69.936775 | H276: 68.2742 | I276: 1.1740594 | J276: 67.243536 | K276: 0.17067292 | L276: 69.936775 | M276: 0
A277: 3 | B277: C4 | C277: free_form_10d | D277: MX2_liquidity_rescue | E277: 71.890209 | F277: 68.32578 | G277: 78.124746 | H277: 70.998337 | I277: 0.89187138 | J277: 68.290359 | K277: 0.035421365 | L277: 77.628703 | M277: 0.49604281
A278: 3 | B278: C6 | C278: free_form_10d | D278: OE2_cost_efficiency_moderate | E278: 72.172397 | F278: 68.499428 | G278: 78.124746 | H278: 70.998337 | I278: 1.1740594 | J278: 68.290359 | K278: 0.20906886 | L278: 77.628703 | M278: 0.49604281
A279: 4 | B279: C4 | C279: free_form_10d | D279: OE2_cost_efficiency_moderate | E279: 77.201711 | F279: 75.875634 | G279: 70.40531 | H279: 75.0503 | I279: 2.1514108 | J279: 75.813074 | K279: 0.062559941 | L279: 69.89615 | M279: 0.50916032
A280: 4 | B280: C6 | C280: free_form_10d | D280: OE2_cost_efficiency_moderate | E280: 77.201711 | F280: 75.89272 | G280: 73.102977 | H280: 75.0503 | I280: 2.1514108 | J280: 75.813074 | K280: 0.07964573 | L280: 69.89615 | M280: 3.206827
A281: 5 | B281: C4 | C281: free_form_10d | D281: OE2_cost_efficiency_moderate | E281: 70.936712 | F281: 68.199531 | G281: 70.814909 | H281: 70.747307 | I281: 0.18940416 | J281: 68.17692 | K281: 0.022611298 | L281: 70.814909 | M281: 0
A282: 5 | B282: C6 | C282: free_form_10d | D282: OE2_cost_efficiency_moderate | E282: 70.936712 | F282: 68.199531 | G282: 70.814909 | H282: 70.747307 | I282: 0.18940416 | J282: 68.17692 | K282: 0.022611298 | L282: 70.814909 | M282: 0
... A520: 124 | B520: C6 | C520: free_form_10d | D520: MX1_cost_and_deleverage | E520: 81.562263 | F520: 73.398278 | G520: 80.362429 | H520: 80.092817 | I520: 1.4694456 | J520: 73.260612 | K520: 0.13766524 | L520: 80.443514 | M520: -0.08108462
A523: 입력 4: frozen_outputs/final_freeze/llm_runs/N5_C6_L1_1p27_ICc_gpt54mini_p50_main_seed1_20260707/stage8_llm_multi_oracle_eval/llm_stage8_multi_oracle_scores.parquet
A524: 파일 크기(bytes) | B524: 76248 | C524: 생산 코드 | D524: src/credit_recourse/analysis/n5_budget_frontier_holm_inference.py | E524: SHA256 | F524: B47635EE85854E031F3B1B51C33CCE28A5DAC08D4DCA3C2B8CFF3997C0110725 | G524: 읽기 상태 | H524: TRUNCATED
A525: row_id | B525: policy | C525: mode | D525: candidate_id | E525: R_score_alpha | F525: R_score_beta | G525: R_score_gamma | H525: noop_R_score_alpha | I525: delta_R_score_alpha | J525: noop_R_score_beta | K525: delta_R_score_beta | L525: noop_R_score_gamma | M525: delta_R_score_gamma
A526: 0 | B526: C4 | C526: free_form_10d | D526: OE1_cost_efficiency_mild | E526: 80.762481 | F526: 71.637147 | G526: 75.239489 | H526: 80.762481 | I526: 0 | J526: 71.550825 | K526: 0.086321612 | L526: 75.110398 | M526: 0.12909112
A527: 0 | B527: C6 | C527: free_form_10d | D527: OE1_cost_efficiency_mild | E527: 80.762481 | F527: 71.700434 | G527: 75.764506 | H527: 80.762481 | I527: 0 | J527: 71.550825 | K527: 0.14960914 | L527: 75.110398 | M527: 0.65410797
A528: 1 | B528: C4 | C528: free_form_10d | D528: OE1_cost_efficiency_mild | E528: 82.740507 | F528: 76.231945 | G528: 78.760402 | H528: 77.977741 | I528: 4.7627666 | J528: 76.119154 | K528: 0.11279106 | L528: 78.841487 | M528: -0.08108462
A529: 1 | B529: C6 | C529: free_form_10d | D529: OE1_cost_efficiency_mild | E529: 81.126606 | F529: 76.194532 | G529: 78.760402 | H529: 77.977741 | I529: 3.1488649 | J529: 76.119154 | K529: 0.075377671 | L529: 78.841487 | M529: -0.08108462
A530: 2 | B530: C4 | C530: free_form_10d | D530: OE2_cost_efficiency_moderate | E530: 68.556388 | F530: 67.390424 | G530: 69.936775 | H530: 68.2742 | I530: 0.28218806 | J530: 67.243536 | K530: 0.14688817 | L530: 69.936775 | M530: 0
A531: 2 | B531: C6 | C531: free_form_10d | D531: OE1_cost_efficiency_mild | E531: 68.556388 | F531: 67.390406 | G531: 69.936775 | H531: 68.2742 | I531: 0.28218806 | J531: 67.243536 | K531: 0.1468695 | L531: 69.936775 | M531: 0
A532: 3 | B532: C4 | C532: free_form_10d | D532: MX1_cost_and_deleverage | E532: 72.172397 | F532: 68.453433 | G532: 78.124746 | H532: 70.998337 | I532: 1.1740594 | J532: 68.290359 | K532: 0.16307392 | L532: 77.628703 | M532: 0.49604281
A533: 3 | B533: C6 | C533: free_form_10d | D533: OE2_cost_efficiency_moderate | E533: 72.172397 | F533: 68.518192 | G533: 78.124746 | H533: 70.998337 | I533: 1.1740594 | J533: 68.290359 | K533: 0.2278333 | L533: 77.628703 | M533: 0.49604281
A534: 4 | B534: C4 | C534: free_form_10d | D534: MX1_cost_and_deleverage | E534: 77.201711 | F534: 75.872105 | G534: 70.40531 | H534: 75.0503 | I534: 2.1514108 | J534: 75.813074 | K534: 0.059030245 | L534: 69.89615 | M534: 0.50916032
A535: 4 | B535: C6 | C535: free_form_10d | D535: OE2_cost_efficiency_moderate | E535: 77.201711 | F535: 75.888512 | G535: 70.40531 | H535: 75.0503 | I535: 2.1514108 | J535: 75.813074 | K535: 0.07543776 | L535: 69.89615 | M535: 0.50916032
A536: 5 | B536: C4 | C536: free_form_10d | D536: OE2_cost_efficiency_moderate | E536: 70.936712 | F536: 68.199531 | G536: 70.814909 | H536: 70.747307 | I536: 0.18940416 | J536: 68.17692 | K536: 0.022611298 | L536: 70.814909 | M536: 0
A537: 5 | B537: C6 | C537: free_form_10d | D537: OE2_cost_efficiency_moderate | E537: 70.936712 | F537: 68.199531 | G537: 70.814909 | H537: 70.747307 | I537: 0.18940416 | J537: 68.17692 | K537: 0.022611298 | L537: 70.814909 | M537: 0
... A775: 124 | B775: C6 | C775: free_form_10d | D775: OE2_cost_efficiency_moderate | E775: 81.562263 | F775: 73.488651 | G775: 82.482582 | H775: 80.092817 | I775: 1.4694456 | J775: 73.260612 | K775: 0.22803884 | L775: 80.443514 | M775: 2.0390682
A778: 입력 5: frozen_outputs/final_freeze/llm_runs/N5_C6_L1_1p27_ICa_gpt54mini_p50_main_seed1_20260707/stage8_llm_multi_oracle_eval/llm_stage8_policy_summary.csv
A779: 파일 크기(bytes) | B779: 689 | C779: 생산 코드 | D779: src/credit_recourse/analysis/n5_budget_frontier_holm_inference.py | E779: SHA256 | F779: 58FB6177BF198A5E84A24479BACDF3E554FD19CCCBBB51B8B1F09FC43E0B45E9 | G779: 읽기 상태 | H779: OK
A780: policy | B780: n_rows | C780: mean_delta_R_score_alpha | D780: median_delta_R_score_alpha | E780: std_delta_R_score_alpha | F780: valid_fraction_alpha | G780: mean_delta_R_score_beta | H780: median_delta_R_score_beta | I780: std_delta_R_score_beta | J780: valid_fraction_beta | K780: mean_delta_R_score_gamma | L780: median_delta_R_score_gamma | M780: std_delta_R_score_gamma | N780: valid_fraction_gamma
A781: C4 | B781: 575 | C781: 0.77532074 | D781: 0.6696426 | E781: 0.92530525 | F781: 1 | G781: 0.13876929 | H781: 0.1337638 | I781: 0.088828007 | J781: 1 | K781: 0.71483902 | L781: 0.44507058 | M781: 0.95235217 | N781: 1
A782: C6 | B782: 575 | C782: 0.89294573 | D782: 0.6749064 | E782: 0.97562913 | F782: 1 | G782: 0.20470794 | H782: 0.17979925 | I782: 0.12884771 | J782: 1 | K782: 0.75845788 | L782: 0.43757673 | M782: 1.0183005 | N782: 1
A785: 입력 6: frozen_outputs/final_freeze/llm_runs/N5_C6_L1_1p27_ICb_gpt54mini_p50_main_seed1_20260707/stage8_llm_multi_oracle_eval/llm_stage8_policy_summary.csv
A786: 파일 크기(bytes) | B786: 691 | C786: 생산 코드 | D786: src/credit_recourse/analysis/n5_budget_frontier_holm_inference.py | E786: SHA256 | F786: 18FBB508E6BC92C9293150972F58F2EBC10A953F45D6A1DC0C2842B341AA58E5 | G786: 읽기 상태 | H786: OK
A787: policy | B787: n_rows | C787: mean_delta_R_score_alpha | D787: median_delta_R_score_alpha | E787: std_delta_R_score_alpha | F787: valid_fraction_alpha | G787: mean_delta_R_score_beta | H787: median_delta_R_score_beta | I787: std_delta_R_score_beta | J787: valid_fraction_beta | K787: mean_delta_R_score_gamma | L787: median_delta_R_score_gamma | M787: std_delta_R_score_gamma | N787: valid_fraction_gamma
A788: C4 | B788: 575 | C788: 0.85983369 | D788: 0.6749064 | E788: 0.91564694 | F788: 1 | G788: 0.14419845 | H788: 0.13227276 | I788: 0.091308015 | J788: 1 | K788: 0.7541247 | L788: 0.45033234 | M788: 0.98306551 | N788: 1
A789: C6 | B789: 575 | C789: 0.88935042 | D789: 0.6749064 | E789: 0.93963891 | F789: 1 | G789: 0.20533056 | H789: 0.17797341 | I789: 0.12920125 | J789: 1 | K789: 0.76161675 | L789: 0.45895988 | M789: 1.0046714 | N789: 1
A792: 입력 7: frozen_outputs/final_freeze/llm_runs/N5_C6_L1_1p27_ICc_gpt54mini_p50_main_seed1_20260707/stage8_llm_multi_oracle_eval/llm_stage8_policy_summary.csv
A793: 파일 크기(bytes) | B793: 692 | C793: 생산 코드 | D793: src/credit_recourse/analysis/n5_budget_frontier_holm_inference.py | E793: SHA256 | F793: 05AFAD7EB655D03700F5C766B29E73C6C8F268BA30E56DF527AD6467186C1D2D | G793: 읽기 상태 | H793: OK
A794: policy | B794: n_rows | C794: mean_delta_R_score_alpha | D794: median_delta_R_score_alpha | E794: std_delta_R_score_alpha | F794: valid_fraction_alpha | G794: mean_delta_R_score_beta | H794: median_delta_R_score_beta | I794: std_delta_R_score_beta | J794: valid_fraction_beta | K794: mean_delta_R_score_gamma | L794: median_delta_R_score_gamma | M794: std_delta_R_score_gamma | N794: valid_fraction_gamma
A795: C4 | B795: 575 | C795: 0.84915576 | D795: 0.6749064 | E795: 0.96815927 | F795: 1 | G795: 0.13890661 | H795: 0.13068855 | I795: 0.089485506 | J795: 1 | K795: 0.74554803 | L795: 0.45895988 | M795: 0.95611758 | N795: 1
A796: C6 | B796: 575 | C796: 0.93458552 | D796: 0.6749064 | E796: 0.97156769 | F796: 1 | G796: 0.20443185 | H796: 0.17285247 | I796: 0.12664533 | J796: 1 | K796: 0.76422488 | L796: 0.45289554 | M796: 0.99661199 | N796: 1

Sheet CALCULATION
A1: T5-6 · 분석 과정
A2: 필터·분석단위와 실제 계산 결과입니다. 수치 셀은 SOURCE를 직접 참조합니다.
A4: 항목 | B4: 내용
A5: 계산 방법 | B5: 같은 기업의 행동 후 Oracle 점수에서 그 기업의 무행동 Oracle 점수를 뺀 뒤 기업 단위로 집계
A6: 생산 코드 | B6: src/credit_recourse/analysis/n5_budget_frontier_holm_inference.py
A7: 선택 실행 | B7: V11_FINAL_FROZEN_REPLAY_RESUME
A11: 동일기업 정책가치 계산
A12: 입력 산출물 | B12: 기업 행 수 | C12: 결합 방식 | D12: 정책가치 정의
A13: frozen_outputs/final_freeze/llm_runs/N5_C6_L1_1p27_ICa_gpt54mini_p50_main_seed1_20260707/stage8_llm_multi_oracle_eval/llm_stage8_multi_oracle_scores.parquet | B13: 1150 | C13: EXPLICIT_NOOP_SCORE_SAME_ROW | D13: 동일기업 행동 점수 − 동일기업 무행동 점수
A14: frozen_outputs/final_freeze/llm_runs/N5_C6_L1_1p27_ICb_gpt54mini_p50_main_seed1_20260707/stage8_llm_multi_oracle_eval/llm_stage8_multi_oracle_scores.parquet | B14: 1150 | C14: EXPLICIT_NOOP_SCORE_SAME_ROW | D14: 동일기업 행동 점수 − 동일기업 무행동 점수
A15: frozen_outputs/final_freeze/llm_runs/N5_C6_L1_1p27_ICc_gpt54mini_p50_main_seed1_20260707/stage8_llm_multi_oracle_eval/llm_stage8_multi_oracle_scores.parquet | B15: 1150 | C15: EXPLICIT_NOOP_SCORE_SAME_ROW | D15: 동일기업 행동 점수 − 동일기업 무행동 점수
A18: 계산 데이터: n5_information_condition_summaries
A19: 입력 파일 | B19: data/final_freeze/llm_runs/N5_C6_L1_1p27_ICa_gpt54mini_p50_main_seed1_20260707/stage8_llm_multi_oracle_eval/llm_stage8_policy_summary.csv; data/final_freeze/llm_runs/N5_C6_L1_1p27_ICb_gpt54mini_p50_main_seed1_20260707/stage8_llm_multi_oracle_eval/llm_stage8_policy_summary.csv; data/final_freeze/llm_runs/N5_C6_L1_1p27_ICc_gpt54mini_p50_main_seed1_20260707/stage8_llm_multi_oracle_eval/llm_stage8_policy_summary.csv
A20: 선택 조건 | B20: [{"column": "policy", "op": "in", "values": ["C4", "C6"]}]
A21: 분석 단위 | B21: source_file; policy
A22: 집계 | B22: PRODUCER_MEAN_AFTER_SAME_FIRM_PAIRING_VERIFIED
A23: source_file | B23: policy | C23: n_rows | D23: mean_delta_R_score_alpha | E23: mean_delta_R_score_beta | F23: mean_delta_R_score_gamma
A24: data/final_freeze/llm_runs/N5_C6_L1_1p27_ICa_gpt54mini_p50_main_seed1_20260707/stage8_llm_multi_oracle_eval/llm_stage8_policy_summary.csv | B24: ='SOURCE'!A781 | C24: ='SOURCE'!B781 | D24: ='SOURCE'!C781 | E24: ='SOURCE'!G781 | F24: ='SOURCE'!K781
A25: data/final_freeze/llm_runs/N5_C6_L1_1p27_ICa_gpt54mini_p50_main_seed1_20260707/stage8_llm_multi_oracle_eval/llm_stage8_policy_summary.csv | B25: ='SOURCE'!A782 | C25: ='SOURCE'!B782 | D25: ='SOURCE'!C782 | E25: ='SOURCE'!G782 | F25: ='SOURCE'!K782
A26: data/final_freeze/llm_runs/N5_C6_L1_1p27_ICb_gpt54mini_p50_main_seed1_20260707/stage8_llm_multi_oracle_eval/llm_stage8_policy_summary.csv | B26: ='SOURCE'!A788 | C26: ='SOURCE'!B788 | D26: ='SOURCE'!C788 | E26: ='SOURCE'!G788 | F26: ='SOURCE'!K788
A27: data/final_freeze/llm_runs/N5_C6_L1_1p27_ICb_gpt54mini_p50_main_seed1_20260707/stage8_llm_multi_oracle_eval/llm_stage8_policy_summary.csv | B27: ='SOURCE'!A789 | C27: ='SOURCE'!B789 | D27: ='SOURCE'!C789 | E27: ='SOURCE'!G789 | F27: ='SOURCE'!K789
A28: data/final_freeze/llm_runs/N5_C6_L1_1p27_ICc_gpt54mini_p50_main_seed1_20260707/stage8_llm_multi_oracle_eval/llm_stage8_policy_summary.csv | B28: ='SOURCE'!A795 | C28: ='SOURCE'!B795 | D28: ='SOURCE'!C795 | E28: ='SOURCE'!G795 | F28: ='SOURCE'!K795
A29: data/final_freeze/llm_runs/N5_C6_L1_1p27_ICc_gpt54mini_p50_main_seed1_20260707/stage8_llm_multi_oracle_eval/llm_stage8_policy_summary.csv | B29: ='SOURCE'!A796 | C29: ='SOURCE'!B796 | D29: ='SOURCE'!C796 | E29: ='SOURCE'!G796 | F29: ='SOURCE'!K796

Sheet PAPER_TABLE
A1: T5-6 · 논문 표 작업용 결과
A2: ANALYSIS에서 계산된 값만 연결한 최종 작업표입니다. Excel에서 정렬·피벗·표시형식만 조정하면 됩니다.
A4: 계산 결과: n5_information_condition_summaries
A5: ='CALCULATION'!A23 | B5: ='CALCULATION'!B23 | C5: ='CALCULATION'!C23 | D5: ='CALCULATION'!D23 | E5: ='CALCULATION'!E23 | F5: ='CALCULATION'!F23
A6: ='CALCULATION'!A24 | B6: ='CALCULATION'!B24 | C6: ='CALCULATION'!C24 | D6: ='CALCULATION'!D24 | E6: ='CALCULATION'!E24 | F6: ='CALCULATION'!F24
A7: ='CALCULATION'!A25 | B7: ='CALCULATION'!B25 | C7: ='CALCULATION'!C25 | D7: ='CALCULATION'!D25 | E7: ='CALCULATION'!E25 | F7: ='CALCULATION'!F25
A8: ='CALCULATION'!A26 | B8: ='CALCULATION'!B26 | C8: ='CALCULATION'!C26 | D8: ='CALCULATION'!D26 | E8: ='CALCULATION'!E26 | F8: ='CALCULATION'!F26
A9: ='CALCULATION'!A27 | B9: ='CALCULATION'!B27 | C9: ='CALCULATION'!C27 | D9: ='CALCULATION'!D27 | E9: ='CALCULATION'!E27 | F9: ='CALCULATION'!F27
A10: ='CALCULATION'!A28 | B10: ='CALCULATION'!B28 | C10: ='CALCULATION'!C28 | D10: ='CALCULATION'!D28 | E10: ='CALCULATION'!E28 | F10: ='CALCULATION'!F28
A11: ='CALCULATION'!A29 | B11: ='CALCULATION'!B29 | C11: ='CALCULATION'!C29 | D11: ='CALCULATION'!D29 | E11: ='CALCULATION'!E29 | F11: ='CALCULATION'!F29
