Workbook

Sheet README
A1: T6-3 · 표 6-3. LLM 응답에서 확인할 문제와 필요한 검토
A2: 논문 인쇄값을 계산 입력으로 쓰지 않고, 선택 실행의 실제 산출물에서 값을 계산한 Excel입니다.
A4: 항목 | B4: 내용
A5: 선택 실행 | B5: V11_FINAL_FROZEN_REPLAY_RESUME
A6: 실행 방식 | B6: FrozenReplay
A7: 논문 항목 읽기 | B7: 논문 DOCX에서 번호·제목·위치만 동적으로 읽음
A8: 논문 위치 | B8: 6.6 파운데이션 모델 간 비교를 위한 실행자료 확인 · 인쇄면 78
A9: 관측·집계 단위 | B9: budget_label + policy
A10: 선택 조건 | B10: 추가 필터 없음
A11: 계산 방법 | B11: 계산 가능한 결과는 실행 산출물에서 계산하고 정의·설정은 별도로 구분
A12: 생산 코드 | B12: Stage7 parser and n5m_posthoc
A13: 실제 입력 산출물 | B13: src/credit_recourse/rl/pipelines/final_stage7_llm_action_generation/response_parser.py frozen_outputs/analysis/paper_repro/03_output_contract_diagnostics/n5m_posthoc/n5m_feasibility_by_budget_policy.csv

Sheet SOURCE
A1: T6-3 · 실제 입력 산출물
A2: 선택 실행에서 읽은 실제 중간·최종 산출물입니다. 아래 ANALYSIS가 이 셀들을 직접 참조합니다.
A4: 입력 1: src/credit_recourse/rl/pipelines/final_stage7_llm_action_generation/response_parser.py
A5: 파일 크기(bytes) | B5: 34873 | C5: 생산 코드 | D5: Stage7 parser and n5m_posthoc | E5: SHA256 | F5: 30DCDA5130E7B0C3DF4EAD225CF5623D882B69DE3F992642F2DCFF0A08627045 | G5: 읽기 상태 | H5: OK
A6: line_number | B6: text
A7: 1 | B7: from __future__ import annotations
A8: 2
A9: 3 | B9: """Stage 7 LLM response parser.
A10: 4
A11: 5 | B11: Responsibilities:
A12: 6
A13: 7 | B13: * Validate the parsed JSON against the mode-specific schema.
A14: 8 | B14: * Materialize the 10D action vector (candidate-selection mode → lookup;
A15: 9 | B15: free-form mode → numeric vector with bound clipping).
A16: 10 | B16: * Project free-form vectors to the v32 vocabulary via the canonical
A17: 11 | B17: ``project_actions_to_candidates`` helper.
A18: 12 | B18: * Classify any failure into the auditable taxonomy from RESEARCH §10:
A19: 13
A20: 14 | B20: * ``direction_error`` — action direction contradicts the LLM's own
A21: 15 | B21: diagnosis (e.g. claims leverage is the weakness but proposes capex).
A22: 16 | B22: * ``magnitude_error`` — magnitude grossly off (we record but do not hard
A23: 17 | B23: fail; bounds enforce upper limit and the projection distance captures
A24: 18 | B24: further deviation).
A25: 19 | B25: * ``feasibility_violation`` — action would violate accounting identities
A26: 20 | B26: that the simulator must plug.
A27: 21 | B27: * ``liquidity_destructive_recourse`` — action visibly cuts liquidity below
A28: 22 | B28: a safe threshold.
A29: 23 | B29: * ``translational_failure`` — JSON missing required fields or wrong shape.
A30: 24 | B30: * ``structural_out_of_scope`` — recommendation describes an action not
A31: 25 | B31: representable in the 10D simulator (mergers, governance, etc.).
... A36: 30 | B36: that appears in the firm_state.
A37: 31
A38: 32 | B38: The parser never silently drops a row; every failure produces a record in
A39: 33 | B39: the failure audit, and the row is either still routed to the simulator
A40: 34 | B40: (with a diagnostic flag) or recorded as ``structural_out_of_scope`` and
A41: 35 | B41: held out of Stage 8.
A42: 36 | B42: """
A43: 37
A44: 38 | B44: import re
A45: 39 | B45: from dataclasses import dataclass
A46: 40 | B46: from typing import Any
A47: 41
A48: 42 | B48: import pandas as pd
A49: 43
A50: 44 | B50: from credit_recourse.rl.common.actions import (
A51: 45 | B51: ActionSpace,
A52: 46 | B52: project_actions_to_candidates,
A53: 47 | B53: )
A54: 48 | B54: from .llm_backends import LLMResponse
A55: 49 | B55: from .budget_contract import BUDGET_AUDIT_COLUMNS, budget_audit_for_action
A56: 50 | B56: from .failure_coder import (
A57: 51 | B57: FAILURE_CODER_VERSION,
A58: 52 | B58: ORACLE_SCORES_USED_FOR_FAILURE_CODING,
A59: 53 | B59: code_direction_error,
A60: 54 | B60: code_magnitude_error,
A61: 55 | B61: )
A62: 56
A63: 57
A64: 58 | B64: GROUNDING_MATCHER_VERSION = "stage7_grounding_alias_v2"
A65: 59
A66: 60
A67: 61 | B67: ALLOWED_FAILURE_TAXONOMY = {
A68: 62 | B68: "direction_error",
A69: 63 | B69: "magnitude_error",
A70: 64 | B70: "feasibility_violation",
A71: 65 | B71: "liquidity_destructive_recourse",
A72: 66 | B72: "translational_failure",
A73: 67 | B73: "structural_out_of_scope",
A74: 68 | B74: "anchoring_or_confirmation_failure",
A75: 69 | B75: "ungrounded_judgment",
A76: 70 | B76: }
A77: 71
A78: 72
A79: 73 | B79: @dataclass
A80: 74 | B80: class ParsedAction:
A81: 75 | B81: """One Stage 7 parsed-and-validated action row.
A82: 76
A83: 77 | B83: All Stage 7 outputs flow from instances of this dataclass; the pipeline
A84: 78 | B84: converts a list of these into the ``llm_stage7_action_table.parquet``.
A85: 79 | B85: """
A86: 80
A87: 81 | B87: row_id: int
A88: 82 | B88: policy: str # C4 / C5 / C6 / C7 / C8
A89: 83 | B89: mode: str # "candidate_selection" or "free_form_10d"
A90: 84 | B90: information_condition: str
A91: 85 | B91: selected_candidate: str # final v32 candidate id (after projection if free-form)
A92: 86 | B92: free_form_action: dict[str, float] | None # raw 10D before projection (free-form only)
A93: 87 | B93: materialized_action: dict[str, float] # final 10D after clipping/lookup
A94: 88 | B94: rationale: str
A95: 89 | B95: diagnosis: dict
A96: 90 | B96: rl_reference_candidate: str | None
A97: 91 | B97: reference_source: str
A98: 92 | B98: reference_draw_seed: int | None
... A125: 119 | B125: budgeted_condition_flag: bool = False
A126: 120
A127: 121
A128: 122 | B128: def _clip_to_bounds(
A129: 123 | B129: vector: dict[str, float], space: ActionSpace
A130: 124 | B130: ) -> tuple[dict[str, float], dict[str, dict]]:
A131: 125 | B131: """Clip a 10D dict to ``final_action_contract`` bounds; record clipping."""
...

Sheet CALCULATION
A1: T6-3 · 분석 과정
A2: 필터·분석단위와 실제 계산 결과입니다. 수치 셀은 SOURCE를 직접 참조합니다.
A4: 항목 | B4: 내용
A5: 계산 방법 | B5: 계산 가능한 결과는 실행 산출물에서 계산하고 정의·설정은 별도로 구분
A6: 생산 코드 | B6: Stage7 parser and n5m_posthoc
A7: 선택 실행 | B7: V11_FINAL_FROZEN_REPLAY_RESUME
A11: 계산 데이터: feasibility_counts
A12: 입력 파일 | B12: data/analysis/paper_repro/03_output_contract_diagnostics/n5m_posthoc/n5m_feasibility_by_budget_policy.csv
A13: 선택 조건 | B13: []
A14: 분석 단위 | B14: budget_label; policy
A15: 집계 | B15: PRODUCER_AGGREGATE_NO_REAGGREGATION
A16: budget_label | B16: l1_budget | C16: policy | D16: n_rows | E16: sustainability_critical_count | F16: sustainability_critical_rate | G16: feasibility_core_violation_count | H16: accounting_check_failure_count | I16: negative_balance_count | J16: preflight_failure_count
A17: ='SOURCE'!A868 | B17: ='SOURCE'!B868 | C17: ='SOURCE'!C868 | D17: ='SOURCE'!D868 | E17: ='SOURCE'!E868 | F17: ='SOURCE'!F868 | G17: ='SOURCE'!G868 | H17: ='SOURCE'!H868 | ... J17: ='SOURCE'!J868
A18: ='SOURCE'!A869 | B18: ='SOURCE'!B869 | C18: ='SOURCE'!C869 | D18: ='SOURCE'!D869 | E18: ='SOURCE'!E869 | F18: ='SOURCE'!F869 | G18: ='SOURCE'!G869 | H18: ='SOURCE'!H869 | ... J18: ='SOURCE'!J869
A19: ='SOURCE'!A870 | B19: ='SOURCE'!B870 | C19: ='SOURCE'!C870 | D19: ='SOURCE'!D870 | E19: ='SOURCE'!E870 | F19: ='SOURCE'!F870 | G19: ='SOURCE'!G870 | H19: ='SOURCE'!H870 | ... J19: ='SOURCE'!J870
A20: ='SOURCE'!A871 | B20: ='SOURCE'!B871 | C20: ='SOURCE'!C871 | D20: ='SOURCE'!D871 | E20: ='SOURCE'!E871 | F20: ='SOURCE'!F871 | G20: ='SOURCE'!G871 | H20: ='SOURCE'!H871 | ... J20: ='SOURCE'!J871
A21: ='SOURCE'!A872 | B21: ='SOURCE'!B872 | C21: ='SOURCE'!C872 | D21: ='SOURCE'!D872 | E21: ='SOURCE'!E872 | F21: ='SOURCE'!F872 | G21: ='SOURCE'!G872 | H21: ='SOURCE'!H872 | ... J21: ='SOURCE'!J872
A22: ='SOURCE'!A873 | B22: ='SOURCE'!B873 | C22: ='SOURCE'!C873 | D22: ='SOURCE'!D873 | E22: ='SOURCE'!E873 | F22: ='SOURCE'!F873 | G22: ='SOURCE'!G873 | H22: ='SOURCE'!H873 | ... J22: ='SOURCE'!J873
A23: ='SOURCE'!A874 | B23: ='SOURCE'!B874 | C23: ='SOURCE'!C874 | D23: ='SOURCE'!D874 | E23: ='SOURCE'!E874 | F23: ='SOURCE'!F874 | G23: ='SOURCE'!G874 | H23: ='SOURCE'!H874 | ... J23: ='SOURCE'!J874
A24: ='SOURCE'!A875 | B24: ='SOURCE'!B875 | C24: ='SOURCE'!C875 | D24: ='SOURCE'!D875 | E24: ='SOURCE'!E875 | F24: ='SOURCE'!F875 | G24: ='SOURCE'!G875 | H24: ='SOURCE'!H875 | ... J24: ='SOURCE'!J875

Sheet PAPER_TABLE
A1: T6-3 · 논문 표 작업용 결과
A2: ANALYSIS에서 계산된 값만 연결한 최종 작업표입니다. Excel에서 정렬·피벗·표시형식만 조정하면 됩니다.
A4: 계산 결과: feasibility_counts
A5: ='CALCULATION'!A16 | B5: ='CALCULATION'!B16 | C5: ='CALCULATION'!C16 | D5: ='CALCULATION'!D16 | E5: ='CALCULATION'!E16 | F5: ='CALCULATION'!F16 | G5: ='CALCULATION'!G16 | H5: ='CALCULATION'!H16 | ... J5: ='CALCULATION'!J16
A6: ='CALCULATION'!A17 | B6: ='CALCULATION'!B17 | C6: ='CALCULATION'!C17 | D6: ='CALCULATION'!D17 | E6: ='CALCULATION'!E17 | F6: ='CALCULATION'!F17 | G6: ='CALCULATION'!G17 | H6: ='CALCULATION'!H17 | ... J6: ='CALCULATION'!J17
A7: ='CALCULATION'!A18 | B7: ='CALCULATION'!B18 | C7: ='CALCULATION'!C18 | D7: ='CALCULATION'!D18 | E7: ='CALCULATION'!E18 | F7: ='CALCULATION'!F18 | G7: ='CALCULATION'!G18 | H7: ='CALCULATION'!H18 | ... J7: ='CALCULATION'!J18
A8: ='CALCULATION'!A19 | B8: ='CALCULATION'!B19 | C8: ='CALCULATION'!C19 | D8: ='CALCULATION'!D19 | E8: ='CALCULATION'!E19 | F8: ='CALCULATION'!F19 | G8: ='CALCULATION'!G19 | H8: ='CALCULATION'!H19 | ... J8: ='CALCULATION'!J19
A9: ='CALCULATION'!A20 | B9: ='CALCULATION'!B20 | C9: ='CALCULATION'!C20 | D9: ='CALCULATION'!D20 | E9: ='CALCULATION'!E20 | F9: ='CALCULATION'!F20 | G9: ='CALCULATION'!G20 | H9: ='CALCULATION'!H20 | ... J9: ='CALCULATION'!J20
A10: ='CALCULATION'!A21 | B10: ='CALCULATION'!B21 | C10: ='CALCULATION'!C21 | D10: ='CALCULATION'!D21 | E10: ='CALCULATION'!E21 | F10: ='CALCULATION'!F21 | G10: ='CALCULATION'!G21 | H10: ='CALCULATION'!H21 | ... J10: ='CALCULATION'!J21
A11: ='CALCULATION'!A22 | B11: ='CALCULATION'!B22 | C11: ='CALCULATION'!C22 | D11: ='CALCULATION'!D22 | E11: ='CALCULATION'!E22 | F11: ='CALCULATION'!F22 | G11: ='CALCULATION'!G22 | H11: ='CALCULATION'!H22 | ... J11: ='CALCULATION'!J22
A12: ='CALCULATION'!A23 | B12: ='CALCULATION'!B23 | C12: ='CALCULATION'!C23 | D12: ='CALCULATION'!D23 | E12: ='CALCULATION'!E23 | F12: ='CALCULATION'!F23 | G12: ='CALCULATION'!G23 | H12: ='CALCULATION'!H23 | ... J12: ='CALCULATION'!J23
A13: ='CALCULATION'!A24 | B13: ='CALCULATION'!B24 | C13: ='CALCULATION'!C24 | D13: ='CALCULATION'!D24 | E13: ='CALCULATION'!E24 | F13: ='CALCULATION'!F24 | G13: ='CALCULATION'!G24 | H13: ='CALCULATION'!H24 | ... J13: ='CALCULATION'!J24
