Workbook

Sheet README
A1: T4-5 · 표 4-5. Candidate-IQL과 무행동·휴리스틱의 비교
A2: 논문 인쇄값을 계산 입력으로 쓰지 않고, 선택 실행의 실제 산출물에서 값을 계산한 Excel입니다.
A4: 항목 | B4: 내용
A5: 선택 실행 | B5: V11_FINAL_FROZEN_REPLAY_RESUME
A6: 실행 방식 | B6: FrozenReplay
A7: 논문 항목 읽기 | B7: 논문 DOCX에서 번호·제목·위치만 동적으로 읽음
A8: 논문 위치 | B8: 4.4 비교정책 Candidate-IQL의 정책가치 · 인쇄면 51
A9: 관측·집계 단위 | B9: source_file + policy_a + policy_b
A10: 선택 조건 | B10: [[{"column": "policy_a", "op": "equals", "value": "C3_candidate_iql"}, {"column": "policy_b", "op": "in", "values": ["C0_noop", "C2_weakest_component_rule"]}]]
A11: 계산 방법 | B11: 같은 기업의 행동 후 Oracle 점수에서 그 기업의 무행동 Oracle 점수를 뺀 뒤 기업 단위로 집계
A12: 생산 코드 | B12: src/credit_recourse/rl/pipelines/final_stage6_candidate_iql_multi_oracle_eval/pipeline.py
A13: 실제 입력 산출물 | B13: frozen_outputs/final_freeze/stage6_candidate_selector_eval/multi_oracle_policy_eval.parquet frozen_outputs/final_freeze/stage6_multi_oracle_eval/policy_paired_inference_alpha.csv frozen_outputs/final_freeze/stage6_multi_oracle_eval/policy_paired_inference_beta.csv frozen_outputs/final_freeze/stage6_multi_oracle_eval/policy_paired_inference_gamma.csv frozen_outputs/final_freeze/stage6_multi_oracle_eval/paired_tests_alpha.csv frozen_outputs/final_freeze/stage6_multi_oracle_eval/paired_tests_beta.csv frozen_outputs/final_freeze/stage6_multi_oracle_eval/paired_tests_gamma.csv

Sheet SOURCE
A1: T4-5 · 실제 입력 산출물
A2: 선택 실행에서 읽은 실제 중간·최종 산출물입니다. 아래 ANALYSIS가 이 셀들을 직접 참조합니다.
A4: 입력 1: frozen_outputs/final_freeze/stage6_candidate_selector_eval/multi_oracle_policy_eval.parquet
A5: 파일 크기(bytes) | B5: 246988 | C5: 생산 코드 | D5: src/credit_recourse/rl/pipelines/final_stage6_candidate_iql_multi_oracle_eval/pipeline.py | E5: SHA256 | F5: 291318BABC39CF3011CA117623D6AD5CB6019A8A917188D51C3A64FE5819D248 | G5: 읽기 상태 | H5: TRUNCATED
A6: row_id | B6: policy | C6: candidate_id | D6: R_score_alpha | E6: R_score_beta | F6: R_score_gamma | G6: derived_policy_type | H6: rerank_k | I6: actor_rank | J6: actor_probability | K6: critic_q_min | L6: q_argmax_scope | M6: delta_R_score_alpha | N6: delta_R_score_beta | O6: delta_R_score_gamma
A7: 0 | B7: C0_noop | C7: A0_noop | D7: 80.762481 | E7: 71.550825 | F7: 75.110398 | M7: 0 | N7: 0 | O7: 0
A8: 0 | B8: C2_weakest_component_rule | C8: C2_weakest_component_rule | D8: 80.762481 | E8: 71.722516 | F8: 75.764506 | M8: 0 | N8: 0.17169084 | O8: 0.65410797
A9: 0 | B9: C3_candidate_iql | C9: DL2_deleverage_moderate | D9: 80.762481 | E9: 71.593999 | F9: 76.714897 | M9: 0 | N9: 0.043174564 | O9: 1.604499
A10: 0 | B10: CX1_capex_discipline | C10: CX1_capex_discipline | D10: 80.762481 | E10: 71.56929 | F10: 75.764506 | M10: 0 | N10: 0.018465438 | O10: 0.65410797
A11: 0 | B11: DL1_deleverage_mild | C11: DL1_deleverage_mild | D11: 80.762481 | E11: 71.573407 | F11: 75.51649 | M11: 0 | N11: 0.022581829 | O11: 0.40609248
A12: 0 | B12: DL2_deleverage_moderate | C12: DL2_deleverage_moderate | D12: 80.762481 | E12: 71.593999 | F12: 76.714897 | M12: 0 | N12: 0.043174564 | O12: 1.604499
A13: 0 | B13: MX1_cost_and_deleverage | C13: MX1_cost_and_deleverage | D13: 80.762481 | E13: 71.645509 | F13: 75.487351 | M13: 0 | N13: 0.094684156 | O13: 0.37695357
A14: 0 | B14: MX2_liquidity_rescue | C14: MX2_liquidity_rescue | D14: 80.762481 | E14: 71.569712 | F14: 75.764506 | M14: 0 | N14: 0.018887343 | O14: 0.65410797
A15: 0 | B15: OE1_cost_efficiency_mild | C15: OE1_cost_efficiency_mild | D15: 80.762481 | E15: 71.637147 | F15: 75.239489 | M15: 0 | N15: 0.086321614 | O15: 0.12909112
A16: 0 | B16: OE2_cost_efficiency_moderate | C16: OE2_cost_efficiency_moderate | D16: 80.762481 | E16: 71.722516 | F16: 75.764506 | M16: 0 | N16: 0.17169084 | O16: 0.65410797
A17: 0 | B17: RF1_short_debt_refinance | C17: RF1_short_debt_refinance | D17: 80.762481 | E17: 71.538728 | F17: 75.110398 | M17: 0 | N17: -0.012096635 | O17: 0
A18: 0 | B18: WC1_working_capital_tightening | C18: WC1_working_capital_tightening | D18: 80.762481 | E18: 71.570855 | F18: 75.764506 | M18: 0 | N18: 0.020030432 | O18: 0.65410797
... A256: 19 | B256: C3_candidate_iql | C256: MX2_liquidity_rescue | D256: 71.639402 | E256: 69.069917 | F256: 74.799192 | M256: 0.6696426 | N256: -0.0011766125 | O256: 0.57390508
A259: 입력 2: frozen_outputs/final_freeze/stage6_multi_oracle_eval/policy_paired_inference_alpha.csv
A260: 파일 크기(bytes) | B260: 64499 | C260: 생산 코드 | D260: src/credit_recourse/rl/pipelines/final_stage6_candidate_iql_multi_oracle_eval/pipeline.py | E260: SHA256 | F260: 42EED0A65F078518B7C6CCEFB8F2D5248DD6BD6C181B1569150159CC4BB355BF | G260: 읽기 상태 | H260: OK
A261: policy_a | B261: policy_b | C261: comparison | D261: n_pairs | E261: mean_diff | F261: median_diff | G261: cluster_se | H261: ci95_lo | I261: ci95_hi | J261: wilcoxon_W | K261: wilcoxon_p | L261: holm_adjusted_p
A262: C2_weakest_component_rule | B262: C0_noop | C262: policy_a_minus_policy_b | D262: 575 | E262: 0.50561586 | F262: 0.14214537 | G262: 0.031963424 | H262: 0.44452751 | I262: 0.56594422 | J262: 316 | K262: 2.8687058e-52 | L262: 8.6634917e-50
A263: C3_candidate_iql | B263: C0_noop | C263: policy_a_minus_policy_b | D263: 575 | E263: 0.63031255 | F263: 0.14214537 | G263: 0.039020557 | H263: 0.55560226 | I263: 0.70426204 | J263: 274.5 | K263: 6.3376685e-49 | L263: 1.8505992e-46
A264: C3_candidate_iql_q_argmax | B264: C0_noop | C264: policy_a_minus_policy_b | D264: 575 | E264: 0.49103939 | F264: 0 | G264: 0.036211647 | H264: 0.42229198 | I264: 0.56150642 | J264: 325 | K264: 5.2060946e-46 | L264: 1.4785309e-43
A265: C3_candidate_iql_q_rerank_at_3 | B265: C0_noop | C265: policy_a_minus_policy_b | D265: 575 | E265: 0.59293687 | F265: 0.14214537 | G265: 0.039921178 | H265: 0.51825961 | I265: 0.67199159 | J265: 303 | K265: 1.7624718e-50 | L265: 5.2874153e-48
A266: C3_candidate_iql_q_rerank_at_5 | B266: C0_noop | C266: policy_a_minus_policy_b | D266: 575 | E266: 0.54447179 | F266: 0.14214537 | G266: 0.039590222 | H266: 0.47347333 | I266: 0.62373631 | J266: 295 | K266: 3.5774015e-49 | L266: 1.0589108e-46
A267: C3_candidate_iql_q_rerank_at_7 | B267: C0_noop | C267: policy_a_minus_policy_b | D267: 575 | E267: 0.51225163 | F267: 0 | G267: 0.035206914 | H267: 0.44894083 | I267: 0.58187828 | J267: 292 | K267: 2.4357788e-47 | L267: 7.015043e-45
A268: C3_candidate_iql_q_rerank_at_9 | B268: C0_noop | C268: policy_a_minus_policy_b | D268: 575 | E268: 0.50993899 | F268: 0 | G268: 0.037046248 | H268: 0.44099994 | I268: 0.58225243 | J268: 289 | K268: 5.1196086e-47 | L268: 1.464208e-44
A269: CX1_capex_discipline | B269: C0_noop | C269: policy_a_minus_policy_b | D269: 575 | E269: 0.20018234 | F269: 0 | G269: 0.015150785 | H269: 0.16828525 | I269: 0.22970899 | J269: 0 | K269: 2.5191859e-30 | L269: 6.2475811e-28
A270: DL1_deleverage_mild | B270: C0_noop | C270: policy_a_minus_policy_b | D270: 575 | E270: 0.27808795 | F270: 0 | G270: 0.032125973 | H270: 0.21330402 | I270: 0.3399555 | J270: 148 | K270: 5.1734233e-23 | L270: 1.2105811e-20
A271: DL2_deleverage_moderate | B271: C0_noop | C271: policy_a_minus_policy_b | D271: 575 | E271: 0.51991642 | F271: 0 | G271: 0.041181675 | H271: 0.44260166 | I271: 0.59937671 | J271: 176 | K271: 6.0851372e-34 | L271: 1.6064762e-31
A272: MX1_cost_and_deleverage | B272: C0_noop | C272: policy_a_minus_policy_b | D272: 575 | E272: 0.50033695 | F272: 0.14214537 | G272: 0.034567219 | H272: 0.43688108 | I272: 0.56912134 | J272: 305 | K272: 1.798785e-50 | L272: 5.3603792e-48
A273: MX2_liquidity_rescue | B273: C0_noop | C273: policy_a_minus_policy_b | D273: 575 | E273: 0.60126837 | F273: 0.52620402 | G273: 0.032086962 | H273: 0.53560229 | I273: 0.65867352 | J273: 390 | K273: 1.0032672e-59 | L273: 3.0499322e-57
... A567: WC1_working_capital_tightening | B567: WC2_supplier_financing | C567: policy_a_minus_policy_b | D567: 575 | E567: -0.17269138 | F567: 0 | G567: 0.019838241 | H567: -0.21180559 | I567: -0.133243 | J567: 4560 | K567: 3.3358929e-16 | L567: 6.605068e-14
A570: 입력 3: frozen_outputs/final_freeze/stage6_multi_oracle_eval/policy_paired_inference_beta.csv
A571: 파일 크기(bytes) | B571: 70936 | C571: 생산 코드 | D571: src/credit_recourse/rl/pipelines/final_stage6_candidate_iql_multi_oracle_eval/pipeline.py | E571: SHA256 | F571: 7D3E3DC216700F63CC8A58B235A8F48C9118DA16CB51C904C17ED511923199DC | G571: 읽기 상태 | H571: OK
A572: policy_a | B572: policy_b | C572: comparison | D572: n_pairs | E572: mean_diff | F572: median_diff | G572: cluster_se | H572: ci95_lo | I572: ci95_hi | J572: wilcoxon_W | K572: wilcoxon_p | L572: holm_adjusted_p
A573: C2_weakest_component_rule | B573: C0_noop | C573: policy_a_minus_policy_b | D573: 575 | E573: 0.13483053 | F573: 0.12601525 | G573: 0.0041995312 | H573: 0.1268212 | I573: 0.14269013 | J573: 537 | K573: 7.5303646e-91 | L573: 1.9127126e-88
A574: C3_candidate_iql | B574: C0_noop | C574: policy_a_minus_policy_b | D574: 575 | E574: 0.07583031 | F574: 0.038370021 | G574: 0.0037390097 | H574: 0.068243345 | I574: 0.083152109 | J574: 1925 | K574: 1.8229094e-77 | L574: 4.0104006e-75
A575: C3_candidate_iql_q_argmax | B575: C0_noop | C575: policy_a_minus_policy_b | D575: 575 | E575: 0.052867882 | F575: 0.024252622 | G575: 0.0032195769 | H575: 0.04729078 | I575: 0.059790288 | J575: 5511 | K575: 4.1258085e-75 | L575: 8.7467139e-73
A576: C3_candidate_iql_q_rerank_at_3 | B576: C0_noop | C576: policy_a_minus_policy_b | D576: 575 | E576: 0.074047808 | F576: 0.038253043 | G576: 0.0036182937 | H576: 0.06700197 | I576: 0.081154407 | J576: 2760 | K576: 5.5426694e-81 | L576: 1.2637286e-78
A577: C3_candidate_iql_q_rerank_at_5 | B577: C0_noop | C577: policy_a_minus_policy_b | D577: 575 | E577: 0.066516573 | F577: 0.03034302 | G577: 0.0033798031 | H577: 0.059796164 | I577: 0.073314316 | J577: 2817 | K577: 5.0571737e-81 | L577: 1.16315e-78
A578: C3_candidate_iql_q_rerank_at_7 | B578: C0_noop | C578: policy_a_minus_policy_b | D578: 575 | E578: 0.058981569 | F578: 0.02800733 | G578: 0.0033443028 | H578: 0.052334043 | I578: 0.065774294 | J578: 4233 | K578: 3.1093497e-76 | L578: 6.6540084e-74
A579: C3_candidate_iql_q_rerank_at_9 | B579: C0_noop | C579: policy_a_minus_policy_b | D579: 575 | E579: 0.056027384 | F579: 0.026682354 | G579: 0.0032971461 | H579: 0.050170782 | I579: 0.062805784 | J579: 5518 | K579: 8.6300419e-74 | L579: 1.7950487e-71
A580: CX1_capex_discipline | B580: C0_noop | C580: policy_a_minus_policy_b | D580: 575 | E580: 0.01275863 | F580: 0.0088786659 | G580: 0.00063300387 | H580: 0.011601148 | I580: 0.014096322 | J580: 0 | K580: 7.1991194e-96 | L580: 2.2029305e-93
A581: DL1_deleverage_mild | B581: C0_noop | C581: policy_a_minus_policy_b | D581: 575 | E581: 0.025003004 | F581: 0.015160503 | G581: 0.0013722061 | H581: 0.022590542 | I581: 0.027819048 | J581: 1661 | K581: 1.5334943e-66 | L581: 3.0056488e-64
A582: DL2_deleverage_moderate | B582: C0_noop | C582: policy_a_minus_policy_b | D582: 575 | E582: 0.043989511 | F582: 0.026249004 | G582: 0.0023920157 | H582: 0.039481882 | I582: 0.048749257 | J582: 1717 | K582: 2.2436261e-66 | L582: 4.3526347e-64
A583: MX1_cost_and_deleverage | B583: C0_noop | C583: policy_a_minus_policy_b | D583: 575 | E583: 0.1090671 | F583: 0.099404208 | G583: 0.0025114926 | H583: 0.10407898 | I583: 0.11383448 | J583: 47 | K583: 9.2023484e-96 | L583: 2.6318717e-93
A584: MX2_liquidity_rescue | B584: C0_noop | C584: policy_a_minus_policy_b | D584: 575 | E584: 0.024037867 | F584: 0.021462729 | G584: 0.0010522485 | H584: 0.022054225 | I584: 0.026187159 | J584: 10192 | K584: 3.6962014e-74 | L584: 7.762023e-72
... A878: WC1_working_capital_tightening | B878: WC2_supplier_financing | C878: policy_a_minus_policy_b | D878: 575 | E878: 0.032480006 | F878: 0.020631466 | G878: 0.0018687687 | H878: 0.02926959 | I878: 0.036268592 | J878: 13998 | K878: 8.8880543e-67 | L878: 1.7598348e-64
A881: 입력 4: frozen_outputs/final_freeze/stage6_multi_oracle_eval/policy_paired_inference_gamma.csv
A882: 파일 크기(bytes) | B882: 65541 | C882: 생산 코드 | D882: src/credit_recourse/rl/pipelines/final_stage6_candidate_iql_multi_oracle_eval/pipeline.py | E882: SHA256 | F882: 172C30D13F1ACB1472DCAFE97758A4BBBEC3D3650F2798E6CF2597383DF9F22D | G882: 읽기 상태 | H882: OK
A883: policy_a | B883: policy_b | C883: comparison | D883: n_pairs | E883: mean_diff | F883: median_diff | G883: cluster_se | H883: ci95_lo | I883: ci95_hi | J883: wilcoxon_W | K883: wilcoxon_p | L883: holm_adjusted_p
A884: C2_weakest_component_rule | B884: C0_noop | C884: policy_a_minus_policy_b | D884: 575 | E884: 0.40174213 | F884: 0.08309367 | G884: 0.027940662 | H884: 0.34881204 | I884: 0.45871922 | J884: 2690 | K884: 1.8523781e-50 | L884: 5.4089441e-48
A885: C3_candidate_iql | B885: C0_noop | C885: policy_a_minus_policy_b | D885: 575 | E885: 0.59478066 | F885: 0.23526326 | G885: 0.034985441 | H885: 0.52437229 | I885: 0.66692412 | J885: 795 | K885: 3.2144441e-57 | L885: 9.7076212e-55
A886: C3_candidate_iql_q_argmax | B886: C0_noop | C886: policy_a_minus_policy_b | D886: 575 | E886: 0.42022202 | F886: 0 | G886: 0.028946753 | H886: 0.36134021 | I886: 0.47607535 | J886: 1301 | K886: 2.0142477e-47 | L886: 5.7204633e-45
A887: C3_candidate_iql_q_rerank_at_3 | B887: C0_noop | C887: policy_a_minus_policy_b | D887: 575 | E887: 0.54779722 | F887: 0.20470528 | G887: 0.032288274 | H887: 0.48509914 | I887: 0.61167998 | J887: 914 | K887: 2.5969599e-57 | L887: 7.894758e-55
A888: C3_candidate_iql_q_rerank_at_5 | B888: C0_noop | C888: policy_a_minus_policy_b | D888: 575 | E888: 0.48881421 | F888: 0.12909112 | G888: 0.032510438 | H888: 0.42878656 | I888: 0.55395435 | J888: 1499 | K888: 1.0766524e-51 | L888: 3.2084241e-49
A889: C3_candidate_iql_q_rerank_at_7 | B889: C0_noop | C889: policy_a_minus_policy_b | D889: 575 | E889: 0.44249055 | F889: 0 | G889: 0.029494394 | H889: 0.38752373 | I889: 0.50153465 | J889: 1568 | K889: 2.2709154e-48 | L889: 6.5856546e-46
A890: C3_candidate_iql_q_rerank_at_9 | B890: C0_noop | C890: policy_a_minus_policy_b | D890: 575 | E890: 0.43291666 | F890: 0 | G890: 0.029399536 | H890: 0.37315302 | I890: 0.48726853 | J890: 1550 | K890: 4.4721434e-48 | L890: 1.279033e-45
A891: CX1_capex_discipline | B891: C0_noop | C891: policy_a_minus_policy_b | D891: 575 | E891: 0.18641058 | F891: 0 | G891: 0.016732087 | H891: 0.15473702 | I891: 0.21818031 | J891: 262 | K891: 5.5949301e-31 | L891: 1.3875427e-28
A892: DL1_deleverage_mild | B892: C0_noop | C892: policy_a_minus_policy_b | D892: 575 | E892: 0.34403744 | F892: 0 | G892: 0.025839393 | H892: 0.29674867 | I892: 0.39584048 | J892: 460 | K892: 1.5061514e-45 | L892: 4.2172238e-43
A893: DL2_deleverage_moderate | B893: C0_noop | C893: policy_a_minus_policy_b | D893: 575 | E893: 0.58403571 | F893: 0.1629485 | G893: 0.037347383 | H893: 0.51062295 | I893: 0.65908361 | J893: 423 | K893: 3.5529694e-53 | L893: 1.0658908e-50
A894: MX1_cost_and_deleverage | B894: C0_noop | C894: policy_a_minus_policy_b | D894: 575 | E894: 0.43885222 | F894: 0.087135813 | G894: 0.029129712 | H894: 0.38258554 | I894: 0.49602084 | J894: 2212 | K894: 1.5756413e-51 | L894: 4.6638981e-49
A895: MX2_liquidity_rescue | B895: C0_noop | C895: policy_a_minus_policy_b | D895: 575 | E895: 0.56648239 | F895: 0.39868127 | G895: 0.030421655 | H895: 0.51141529 | I895: 0.62625511 | J895: 2155 | K895: 9.8082322e-65 | L895: 3.0013191e-62
... A1189: WC1_working_capital_tightening | B1189: WC2_supplier_financing | C1189: policy_a_minus_policy_b | D1189: 575 | E1189: -0.1474039 | F1189: 0 | G1189: 0.017068138 | H1189: -0.18174614 | I1189: -0.11451312 | J1189: 4567 | K1189: 4.6256241e-24 | L1189: 1.0083861e-21
A1192: 입력 5: frozen_outputs/final_freeze/stage6_multi_oracle_eval/paired_tests_alpha.csv
A1193: 파일 크기(bytes) | B1193: 2601 | C1193: 생산 코드 | D1193: src/credit_recourse/rl/pipelines/final_stage6_candidate_iql_multi_oracle_eval/pipeline.py | E1193: SHA256 | F1193: DC6DD3A6929692C54CAE747E44B6D5F7275AB92026906C8B6E62D93A0DA2D6DE | G1193: 읽기 상태 | H1193: OK
A1194: policy | B1194: reference | C1194: n | D1194: mean_diff | E1194: median_diff
A1195: C2_weakest_component_rule | B1195: C0_noop | C1195: 575 | D1195: 0.50561586 | E1195: 0.14214537
A1196: C3_candidate_iql | B1196: C0_noop | C1196: 575 | D1196: 0.63031255 | E1196: 0.14214537
A1197: C3_candidate_iql_q_argmax | B1197: C0_noop | C1197: 575 | D1197: 0.49103939 | E1197: 0
A1198: C3_candidate_iql_q_rerank_at_3 | B1198: C0_noop | C1198: 575 | D1198: 0.59293687 | E1198: 0.14214537
A1199: C3_candidate_iql_q_rerank_at_5 | B1199: C0_noop | C1199: 575 | D1199: 0.54447179 | E1199: 0.14214537
A1200: C3_candidate_iql_q_rerank_at_7 | B1200: C0_noop | C1200: 575 | D1200: 0.51225163 | E1200: 0
A1201: C3_candidate_iql_q_rerank_at_9 | B1201: C0_noop | C1201: 575 | D1201: 0.50993899 | E1201: 0
A1202: CX1_capex_discipline | B1202: C0_noop | C1202: 575 | D1202: 0.20018234 | E1202: 0
A1203: DL1_deleverage_mild | B1203: C0_noop | C1203: 575 | D1203: 0.27808795 | E1203: 0
A1204: DL2_deleverage_moderate | B1204: C0_noop | C1204: 575 | D1204: 0.51991642 | E1204: 0
A1205: MX1_cost_and_deleverage | B1205: C0_noop | C1205: 575 | D1205: 0.50033695 | E1205: 0.14214537
A1206: MX2_liquidity_rescue | B1206: C0_noop | C1206: 575 | D1206: 0.60126837 | E1206: 0.52620402
... A1228: WC2_supplier_financing | B1228: C2_weakest_component_rule | C1228: 575 | D1228: -0.026156858 | E1228: 0
A1231: 입력 6: frozen_outputs/final_freeze/stage6_multi_oracle_eval/paired_tests_beta.csv
A1232: 파일 크기(bytes) | B1232: 3031 | C1232: 생산 코드 | D1232: src/credit_recourse/rl/pipelines/final_stage6_candidate_iql_multi_oracle_eval/pipeline.py | E1232: SHA256 | F1232: FE0C592F09393165CAD33011F0A06DDE58236240FC2B46A1CC73A06C4170FC56 | G1232: 읽기 상태 | H1232: OK
A1233: policy | B1233: reference | C1233: n | D1233: mean_diff | E1233: median_diff
A1234: C2_weakest_component_rule | B1234: C0_noop | C1234: 575 | D1234: 0.13483053 | E1234: 0.12601525
A1235: C3_candidate_iql | B1235: C0_noop | C1235: 575 | D1235: 0.07583031 | E1235: 0.038370021
A1236: C3_candidate_iql_q_argmax | B1236: C0_noop | C1236: 575 | D1236: 0.052867882 | E1236: 0.024252622
A1237: C3_candidate_iql_q_rerank_at_3 | B1237: C0_noop | C1237: 575 | D1237: 0.074047808 | E1237: 0.038253043
A1238: C3_candidate_iql_q_rerank_at_5 | B1238: C0_noop | C1238: 575 | D1238: 0.066516573 | E1238: 0.03034302
A1239: C3_candidate_iql_q_rerank_at_7 | B1239: C0_noop | C1239: 575 | D1239: 0.058981569 | E1239: 0.02800733
A1240: C3_candidate_iql_q_rerank_at_9 | B1240: C0_noop | C1240: 575 | D1240: 0.056027384 | E1240: 0.026682354
A1241: CX1_capex_discipline | B1241: C0_noop | C1241: 575 | D1241: 0.01275863 | E1241: 0.0088786659
A1242: DL1_deleverage_mild | B1242: C0_noop | C1242: 575 | D1242: 0.025003004 | E1242: 0.015160503
A1243: DL2_deleverage_moderate | B1243: C0_noop | C1243: 575 | D1243: 0.043989511 | E1243: 0.026249004
A1244: MX1_cost_and_deleverage | B1244: C0_noop | C1244: 575 | D1244: 0.1090671 | E1244: 0.099404208
A1245: MX2_liquidity_rescue | B1245: C0_noop | C1245: 575 | D1245: 0.024037867 | E1245: 0.021462729
... A1267: WC2_supplier_financing | B1267: C2_weakest_component_rule | C1267: 575 | D1267: -0.14886202 | E1267: -0.12810525
A1270: 입력 7: frozen_outputs/final_freeze/stage6_multi_oracle_eval/paired_tests_gamma.csv
A1271: 파일 크기(bytes) | B1271: 2611 | C1271: 생산 코드 | D1271: src/credit_recourse/rl/pipelines/final_stage6_candidate_iql_multi_oracle_eval/pipeline.py | E1271: SHA256 | F1271: 9CC36FFCCB9E144761519A30304889B707D99F1F1DA8222FC855237C82CD81BC | G1271: 읽기 상태 | H1271: OK
...

Sheet CALCULATION
A1: T4-5 · 분석 과정
A2: 필터·분석단위와 실제 계산 결과입니다. 수치 셀은 SOURCE를 직접 참조합니다.
A4: 항목 | B4: 내용
A5: 계산 방법 | B5: 같은 기업의 행동 후 Oracle 점수에서 그 기업의 무행동 Oracle 점수를 뺀 뒤 기업 단위로 집계
A6: 생산 코드 | B6: src/credit_recourse/rl/pipelines/final_stage6_candidate_iql_multi_oracle_eval/pipeline.py
A7: 선택 실행 | B7: V11_FINAL_FROZEN_REPLAY_RESUME
A11: 이 표·그림과 연결된 본문 핵심 수치
A12: 수치 ID | B12: 본문 주장 | C12: 논문 표시값 | D12: 재계산값 | E12: 확인 결과 | F12: 계산식 | G12: 실제 입력 산출물
A13: NC0127-01 | B13: Candidate-IQL의 무행동 대비 정책가치는 Oracle-α에서 +0.630, β에서 +0.076, γ에서 +0.595였으며 세 Oracle에서 모두 유의하였다. 휴리스틱과 비교한 C3−C2는 α에서 +0.125였지만 유의하지 않았고, β에서는 −0.059, γ에서는 +0.193이었다. Candidate-IQL은 세 Oracle에서 모두 무행동보다 높은 정책가치를 보였지만, 휴리스틱보다 항상 높은 정책가치를 보인 것은 아니다. 따라서 Candidate-IQL은 최고 성능의 정책이 아니라 LLM 정책과 비교하기 위한 기준정책으로 사용한다. | C13: +0.630 | D13: 0.63 | E13: 논문값과 일치 | F13: MEAN_i(R_score_alpha(action_i) - R_score_alpha(noop_i)) | G13: frozen_outputs/final_freeze/stage6_multi_oracle_eval/final_policy_summary.csv
A14: NC0127-02 | B14: Candidate-IQL의 무행동 대비 정책가치는 Oracle-α에서 +0.630, β에서 +0.076, γ에서 +0.595였으며 세 Oracle에서 모두 유의하였다. 휴리스틱과 비교한 C3−C2는 α에서 +0.125였지만 유의하지 않았고, β에서는 −0.059, γ에서는 +0.193이었다. Candidate-IQL은 세 Oracle에서 모두 무행동보다 높은 정책가치를 보였지만, 휴리스틱보다 항상 높은 정책가치를 보인 것은 아니다. 따라서 Candidate-IQL은 최고 성능의 정책이 아니라 LLM 정책과 비교하기 위한 기준정책으로 사용한다. | C14: +0.076 | D14: 0.076 | E14: 논문값과 일치 | F14: MEAN_i(R_score_beta(action_i) - R_score_beta(noop_i)) | G14: frozen_outputs/final_freeze/stage6_multi_oracle_eval/final_policy_summary.csv
A15: NC0127-03 | B15: Candidate-IQL의 무행동 대비 정책가치는 Oracle-α에서 +0.630, β에서 +0.076, γ에서 +0.595였으며 세 Oracle에서 모두 유의하였다. 휴리스틱과 비교한 C3−C2는 α에서 +0.125였지만 유의하지 않았고, β에서는 −0.059, γ에서는 +0.193이었다. Candidate-IQL은 세 Oracle에서 모두 무행동보다 높은 정책가치를 보였지만, 휴리스틱보다 항상 높은 정책가치를 보인 것은 아니다. 따라서 Candidate-IQL은 최고 성능의 정책이 아니라 LLM 정책과 비교하기 위한 기준정책으로 사용한다. | C15: +0.595 | D15: 0.595 | E15: 논문값과 일치 | F15: MEAN_i(R_score_gamma(action_i) - R_score_gamma(noop_i)) | G15: frozen_outputs/final_freeze/stage6_multi_oracle_eval/final_policy_summary.csv
A16: NC0127-04 | B16: Candidate-IQL의 무행동 대비 정책가치는 Oracle-α에서 +0.630, β에서 +0.076, γ에서 +0.595였으며 세 Oracle에서 모두 유의하였다. 휴리스틱과 비교한 C3−C2는 α에서 +0.125였지만 유의하지 않았고, β에서는 −0.059, γ에서는 +0.193이었다. Candidate-IQL은 세 Oracle에서 모두 무행동보다 높은 정책가치를 보였지만, 휴리스틱보다 항상 높은 정책가치를 보인 것은 아니다. 따라서 Candidate-IQL은 최고 성능의 정책이 아니라 LLM 정책과 비교하기 위한 기준정책으로 사용한다. | C16: +0.125 | D16: 0.125 | E16: 논문값과 일치 | F16: 575개 동일 기업 각각에서 Candidate-IQL 정책가치에서 최약요인 휴리스틱 정책가치를 뺀 뒤 평균 (alpha); 선택 실행 Stage6의 575개 기업 행을 row_id로 직접 대응해 재계산 | G16: frozen_outputs/final_freeze/stage6_candidate_selector_eval/multi_oracle_policy_eval.parquet embedded://thesis-output-calculation/derived/reviewer_core_direct_calculations.csv
A17: NC0127-05 | B17: Candidate-IQL의 무행동 대비 정책가치는 Oracle-α에서 +0.630, β에서 +0.076, γ에서 +0.595였으며 세 Oracle에서 모두 유의하였다. 휴리스틱과 비교한 C3−C2는 α에서 +0.125였지만 유의하지 않았고, β에서는 −0.059, γ에서는 +0.193이었다. Candidate-IQL은 세 Oracle에서 모두 무행동보다 높은 정책가치를 보였지만, 휴리스틱보다 항상 높은 정책가치를 보인 것은 아니다. 따라서 Candidate-IQL은 최고 성능의 정책이 아니라 LLM 정책과 비교하기 위한 기준정책으로 사용한다. | C17: −0.059 | D17: -0.059 | E17: 논문값과 일치 | F17: 575개 동일 기업 각각에서 Candidate-IQL 정책가치에서 최약요인 휴리스틱 정책가치를 뺀 뒤 평균 (beta); 선택 실행 Stage6의 575개 기업 행을 row_id로 직접 대응해 재계산 | G17: frozen_outputs/final_freeze/stage6_candidate_selector_eval/multi_oracle_policy_eval.parquet embedded://thesis-output-calculation/derived/reviewer_core_direct_calculations.csv
A18: NC0127-06 | B18: Candidate-IQL의 무행동 대비 정책가치는 Oracle-α에서 +0.630, β에서 +0.076, γ에서 +0.595였으며 세 Oracle에서 모두 유의하였다. 휴리스틱과 비교한 C3−C2는 α에서 +0.125였지만 유의하지 않았고, β에서는 −0.059, γ에서는 +0.193이었다. Candidate-IQL은 세 Oracle에서 모두 무행동보다 높은 정책가치를 보였지만, 휴리스틱보다 항상 높은 정책가치를 보인 것은 아니다. 따라서 Candidate-IQL은 최고 성능의 정책이 아니라 LLM 정책과 비교하기 위한 기준정책으로 사용한다. | C18: +0.193 | D18: 0.193 | E18: 논문값과 일치 | F18: 575개 동일 기업 각각에서 Candidate-IQL 정책가치에서 최약요인 휴리스틱 정책가치를 뺀 뒤 평균 (gamma); 선택 실행 Stage6의 575개 기업 행을 row_id로 직접 대응해 재계산 | G18: frozen_outputs/final_freeze/stage6_candidate_selector_eval/multi_oracle_policy_eval.parquet embedded://thesis-output-calculation/derived/reviewer_core_direct_calculations.csv
A21: 동일기업 정책가치 계산
A22: 입력 산출물 | B22: 기업 행 수 | C22: 결합 방식 | D22: 정책가치 정의
A23: frozen_outputs/final_freeze/stage6_candidate_selector_eval/multi_oracle_policy_eval.parquet | B23: 10350 | C23: ROW_ID_TO_UNIQUE_NOOP_POLICY_JOIN | D23: 동일기업 행동 점수 − 동일기업 무행동 점수
A26: 계산 데이터: stage6_paired_inference
A27: 입력 파일 | B27: data/final_freeze/stage6_multi_oracle_eval/policy_paired_inference_alpha.csv; data/final_freeze/stage6_multi_oracle_eval/policy_paired_inference_beta.csv; data/final_freeze/stage6_multi_oracle_eval/policy_paired_inference_gamma.csv
A28: 선택 조건 | B28: [{"column": "policy_a", "op": "equals", "value": "C3_candidate_iql"}, {"column": "policy_b", "op": "in", "values": ["C0_noop", "C2_weakest_component_rule"]}]
A29: 분석 단위 | B29: source_file; policy_a; policy_b
A30: 집계 | B30: PRODUCER_MEAN_AFTER_SAME_FIRM_PAIRING_VERIFIED
A31: source_file | B31: policy_a | C31: policy_b | D31: n_pairs | E31: mean_diff | F31: cluster_se | G31: ci95_lo | H31: ci95_hi | I31: wilcoxon_p | J31: holm_adjusted_p
A32: data/final_freeze/stage6_multi_oracle_eval/policy_paired_inference_alpha.csv | B32: ='SOURCE'!A263 | C32: ='SOURCE'!B263 | D32: ='SOURCE'!D263 | E32: ='SOURCE'!E263 | F32: ='SOURCE'!G263 | G32: ='SOURCE'!H263 | H32: ='SOURCE'!I263 | I32: ='SOURCE'!K263 | J32: ='SOURCE'!L263
A33: data/final_freeze/stage6_multi_oracle_eval/policy_paired_inference_alpha.csv | B33: ='SOURCE'!A280 | C33: ='SOURCE'!B280 | D33: ='SOURCE'!D280 | E33: ='SOURCE'!E280 | F33: ='SOURCE'!G280 | G33: ='SOURCE'!H280 | H33: ='SOURCE'!I280 | I33: ='SOURCE'!K280 | J33: ='SOURCE'!L280
A34: data/final_freeze/stage6_multi_oracle_eval/policy_paired_inference_beta.csv | B34: ='SOURCE'!A574 | C34: ='SOURCE'!B574 | D34: ='SOURCE'!D574 | E34: ='SOURCE'!E574 | F34: ='SOURCE'!G574 | G34: ='SOURCE'!H574 | H34: ='SOURCE'!I574 | I34: ='SOURCE'!K574 | J34: ='SOURCE'!L574
A35: data/final_freeze/stage6_multi_oracle_eval/policy_paired_inference_beta.csv | B35: ='SOURCE'!A591 | C35: ='SOURCE'!B591 | D35: ='SOURCE'!D591 | E35: ='SOURCE'!E591 | F35: ='SOURCE'!G591 | G35: ='SOURCE'!H591 | H35: ='SOURCE'!I591 | I35: ='SOURCE'!K591 | J35: ='SOURCE'!L591
A36: data/final_freeze/stage6_multi_oracle_eval/policy_paired_inference_gamma.csv | B36: ='SOURCE'!A885 | C36: ='SOURCE'!B885 | D36: ='SOURCE'!D885 | E36: ='SOURCE'!E885 | F36: ='SOURCE'!G885 | G36: ='SOURCE'!H885 | H36: ='SOURCE'!I885 | I36: ='SOURCE'!K885 | J36: ='SOURCE'!L885
A37: data/final_freeze/stage6_multi_oracle_eval/policy_paired_inference_gamma.csv | B37: ='SOURCE'!A902 | C37: ='SOURCE'!B902 | D37: ='SOURCE'!D902 | E37: ='SOURCE'!E902 | F37: ='SOURCE'!G902 | G37: ='SOURCE'!H902 | H37: ='SOURCE'!I902 | I37: ='SOURCE'!K902 | J37: ='SOURCE'!L902

Sheet PAPER_TABLE
A1: T4-5 · 논문 표 작업용 결과
A2: ANALYSIS에서 계산된 값만 연결한 최종 작업표입니다. Excel에서 정렬·피벗·표시형식만 조정하면 됩니다.
A4: 계산 결과: stage6_paired_inference
A5: ='CALCULATION'!A31 | B5: ='CALCULATION'!B31 | C5: ='CALCULATION'!C31 | D5: ='CALCULATION'!D31 | E5: ='CALCULATION'!E31 | F5: ='CALCULATION'!F31 | G5: ='CALCULATION'!G31 | H5: ='CALCULATION'!H31 | ... J5: ='CALCULATION'!J31
A6: ='CALCULATION'!A32 | B6: ='CALCULATION'!B32 | C6: ='CALCULATION'!C32 | D6: ='CALCULATION'!D32 | E6: ='CALCULATION'!E32 | F6: ='CALCULATION'!F32 | G6: ='CALCULATION'!G32 | H6: ='CALCULATION'!H32 | ... J6: ='CALCULATION'!J32
A7: ='CALCULATION'!A33 | B7: ='CALCULATION'!B33 | C7: ='CALCULATION'!C33 | D7: ='CALCULATION'!D33 | E7: ='CALCULATION'!E33 | F7: ='CALCULATION'!F33 | G7: ='CALCULATION'!G33 | H7: ='CALCULATION'!H33 | ... J7: ='CALCULATION'!J33
A8: ='CALCULATION'!A34 | B8: ='CALCULATION'!B34 | C8: ='CALCULATION'!C34 | D8: ='CALCULATION'!D34 | E8: ='CALCULATION'!E34 | F8: ='CALCULATION'!F34 | G8: ='CALCULATION'!G34 | H8: ='CALCULATION'!H34 | ... J8: ='CALCULATION'!J34
A9: ='CALCULATION'!A35 | B9: ='CALCULATION'!B35 | C9: ='CALCULATION'!C35 | D9: ='CALCULATION'!D35 | E9: ='CALCULATION'!E35 | F9: ='CALCULATION'!F35 | G9: ='CALCULATION'!G35 | H9: ='CALCULATION'!H35 | ... J9: ='CALCULATION'!J35
A10: ='CALCULATION'!A36 | B10: ='CALCULATION'!B36 | C10: ='CALCULATION'!C36 | D10: ='CALCULATION'!D36 | E10: ='CALCULATION'!E36 | F10: ='CALCULATION'!F36 | G10: ='CALCULATION'!G36 | H10: ='CALCULATION'!H36 | ... J10: ='CALCULATION'!J36
A11: ='CALCULATION'!A37 | B11: ='CALCULATION'!B37 | C11: ='CALCULATION'!C37 | D11: ='CALCULATION'!D37 | E11: ='CALCULATION'!E37 | F11: ='CALCULATION'!F37 | G11: ='CALCULATION'!G37 | H11: ='CALCULATION'!H37 | ... J11: ='CALCULATION'!J37
