Workbook

Sheet README
A1: F4 · 그림 4. Oracle별 표준행동 선호 양상
A2: 논문 인쇄값을 계산 입력으로 쓰지 않고, 선택 실행의 실제 산출물에서 값을 계산한 Excel입니다.
A4: 항목 | B4: 내용
A5: 선택 실행 | B5: V11_FINAL_FROZEN_REPLAY_RESUME
A6: 실행 방식 | B6: FrozenReplay
A7: 논문 항목 읽기 | B7: 논문 DOCX에서 번호·제목·위치만 동적으로 읽음
A8: 논문 위치 | B8: 4.3 Oracle별 정책행동의 신용평점 차이와 동률 · 인쇄면 49
A9: 관측·집계 단위 | B9: json_path; policy
A10: 선택 조건 | B10: [[{"column": "json_path", "op": "equals", "value": "per_backend.alpha.oracle_best_mean_noop_adjusted_score"}]]
A11: 계산 방법 | B11: 같은 기업의 행동 후 Oracle 점수에서 그 기업의 무행동 Oracle 점수를 뺀 뒤 기업 단위로 집계
A12: 생산 코드 | B12: src/credit_recourse/rl/pipelines/final_stage6_candidate_iql_multi_oracle_eval/pipeline.py
A13: 실제 입력 산출물 | B13: frozen_outputs/final_freeze/stage6_candidate_selector_eval/multi_oracle_policy_eval.parquet frozen_outputs/final_freeze/stage6_multi_oracle_eval/iql_q_rerank_candidate_distribution.csv frozen_outputs/final_freeze/stage6_multi_oracle_eval/summary_by_policy_alpha.csv frozen_outputs/final_freeze/stage6_multi_oracle_eval/summary_by_policy_beta.csv frozen_outputs/final_freeze/stage6_multi_oracle_eval/summary_by_policy_gamma.csv frozen_outputs/final_freeze/stage6_multi_oracle_eval/final_policy_summary.csv frozen_outputs/final_freeze/stage6_candidate_selector_eval/derived_comparators_runtime.json

Sheet SOURCE
A1: F4 · 실제 입력 산출물
A2: 선택 실행에서 읽은 실제 중간·최종 산출물입니다. 아래 ANALYSIS가 이 셀들을 직접 참조합니다.
A4: 입력 1: frozen_outputs/final_freeze/stage6_candidate_selector_eval/multi_oracle_policy_eval.parquet
A5: 파일 크기(bytes) | B5: 246988 | C5: 생산 코드 | D5: src/credit_recourse/rl/pipelines/final_stage6_candidate_iql_multi_oracle_eval/pipeline.py | E5: SHA256 | F5: 291318BABC39CF3011CA117623D6AD5CB6019A8A917188D51C3A64FE5819D248 | G5: 읽기 상태 | H5: TRUNCATED
A6: row_id | B6: policy | C6: candidate_id | D6: R_score_alpha | E6: R_score_beta | F6: R_score_gamma | G6: derived_policy_type | H6: rerank_k | I6: actor_rank | J6: actor_probability | K6: critic_q_min | L6: q_argmax_scope | M6: delta_R_score_alpha | N6: delta_R_score_beta | O6: delta_R_score_gamma
A7: 0 | B7: C0_noop | C7: A0_noop | D7: 80.762481 | E7: 71.550825 | F7: 75.110398 | M7: 0 | N7: 0 | O7: 0
A8: 0 | B8: C2_weakest_component_rule | C8: C2_weakest_component_rule | D8: 80.762481 | E8: 71.722516 | F8: 75.764506 | M8: 0 | N8: 0.17169084 | O8: 0.65410797
A9: 0 | B9: C3_candidate_iql | C9: DL2_deleverage_moderate | D9: 80.762481 | E9: 71.593999 | F9: 76.714897 | M9: 0 | N9: 0.043174564 | O9: 1.604499
A10: 0 | B10: CX1_capex_discipline | C10: CX1_capex_discipline | D10: 80.762481 | E10: 71.56929 | F10: 75.764506 | M10: 0 | N10: 0.018465438 | O10: 0.65410797
A11: 0 | B11: DL1_deleverage_mild | C11: DL1_deleverage_mild | D11: 80.762481 | E11: 71.573407 | F11: 75.51649 | M11: 0 | N11: 0.022581829 | O11: 0.40609248
A12: 0 | B12: DL2_deleverage_moderate | C12: DL2_deleverage_moderate | D12: 80.762481 | E12: 71.593999 | F12: 76.714897 | M12: 0 | N12: 0.043174564 | O12: 1.604499
A13: 0 | B13: MX1_cost_and_deleverage | C13: MX1_cost_and_deleverage | D13: 80.762481 | E13: 71.645509 | F13: 75.487351 | M13: 0 | N13: 0.094684156 | O13: 0.37695357
A14: 0 | B14: MX2_liquidity_rescue | C14: MX2_liquidity_rescue | D14: 80.762481 | E14: 71.569712 | F14: 75.764506 | M14: 0 | N14: 0.018887343 | O14: 0.65410797
A15: 0 | B15: OE1_cost_efficiency_mild | C15: OE1_cost_efficiency_mild | D15: 80.762481 | E15: 71.637147 | F15: 75.239489 | M15: 0 | N15: 0.086321614 | O15: 0.12909112
A16: 0 | B16: OE2_cost_efficiency_moderate | C16: OE2_cost_efficiency_moderate | D16: 80.762481 | E16: 71.722516 | F16: 75.764506 | M16: 0 | N16: 0.17169084 | O16: 0.65410797
A17: 0 | B17: RF1_short_debt_refinance | C17: RF1_short_debt_refinance | D17: 80.762481 | E17: 71.538728 | F17: 75.110398 | M17: 0 | N17: -0.012096635 | O17: 0
A18: 0 | B18: WC1_working_capital_tightening | C18: WC1_working_capital_tightening | D18: 80.762481 | E18: 71.570855 | F18: 75.764506 | M18: 0 | N18: 0.020030432 | O18: 0.65410797
... A256: 19 | B256: C3_candidate_iql | C256: MX2_liquidity_rescue | D256: 71.639402 | E256: 69.069917 | F256: 74.799192 | M256: 0.6696426 | N256: -0.0011766125 | O256: 0.57390508
A259: 입력 2: frozen_outputs/final_freeze/stage6_multi_oracle_eval/iql_q_rerank_candidate_distribution.csv
A260: 파일 크기(bytes) | B260: 2567 | C260: 생산 코드 | D260: src/credit_recourse/rl/pipelines/final_stage6_candidate_iql_multi_oracle_eval/pipeline.py | E260: SHA256 | F260: C4F6D040EF0A23B46A2CE16FF03DF3B727899FE273D5D42186AE0836903EFE05 | G260: 읽기 상태 | H260: OK
A261: policy | B261: candidate_id | C261: count
A262: C3_candidate_iql_q_rerank_at_3 | B262: DL2_deleverage_moderate | C262: 219
A263: C3_candidate_iql_q_rerank_at_3 | B263: WC1_working_capital_tightening | C263: 130
A264: C3_candidate_iql_q_rerank_at_3 | B264: OE2_cost_efficiency_moderate | C264: 104
A265: C3_candidate_iql_q_rerank_at_3 | B265: MX2_liquidity_rescue | C265: 52
A266: C3_candidate_iql_q_rerank_at_3 | B266: MX1_cost_and_deleverage | C266: 49
A267: C3_candidate_iql_q_rerank_at_3 | B267: A0_noop | C267: 8
A268: C3_candidate_iql_q_rerank_at_3 | B268: RF1_short_debt_refinance | C268: 5
A269: C3_candidate_iql_q_rerank_at_3 | B269: WC2_supplier_financing | C269: 3
A270: C3_candidate_iql_q_rerank_at_3 | B270: CX1_capex_discipline | C270: 2
A271: C3_candidate_iql_q_rerank_at_3 | B271: OE1_cost_efficiency_mild | C271: 2
A272: C3_candidate_iql_q_rerank_at_3 | B272: DL1_deleverage_mild | C272: 1
A273: C3_candidate_iql_q_rerank_at_5 | B273: DL2_deleverage_moderate | C273: 182
... A305: C3_candidate_iql_q_rerank_at_9 | B305: OE1_cost_efficiency_mild | C305: 7
A308: 입력 3: frozen_outputs/final_freeze/stage6_multi_oracle_eval/summary_by_policy_alpha.csv
A309: 파일 크기(bytes) | B309: 1532 | C309: 생산 코드 | D309: src/credit_recourse/rl/pipelines/final_stage6_candidate_iql_multi_oracle_eval/pipeline.py | E309: SHA256 | F309: B00CD717633BCDA601A233469069FB67B3B04852EC8ED5036FB2E4E7260398F0 | G309: 읽기 상태 | H309: OK
A310: policy | B310: count | C310: mean | D310: median | E310: std
A311: C0_noop | B311: 575 | C311: 68.758255 | D311: 69.677193 | E311: 7.876943
A312: C2_weakest_component_rule | B312: 575 | C312: 69.26387 | D312: 70.10155 | E312: 7.9268328
A313: C3_candidate_iql | B313: 575 | C313: 69.388567 | D313: 70.145398 | E313: 7.834502
A314: C3_candidate_iql_q_argmax | B314: 575 | C314: 69.249294 | D314: 70.118983 | E314: 7.9115837
A315: C3_candidate_iql_q_rerank_at_3 | B315: 575 | C315: 69.351192 | D315: 70.145398 | E315: 7.8598415
A316: C3_candidate_iql_q_rerank_at_5 | B316: 575 | C316: 69.302726 | D316: 70.145398 | E316: 7.8895594
A317: C3_candidate_iql_q_rerank_at_7 | B317: 575 | C317: 69.270506 | D317: 70.118983 | E317: 7.9079654
A318: C3_candidate_iql_q_rerank_at_9 | B318: 575 | C318: 69.268194 | D318: 70.118983 | E318: 7.9083814
A319: CX1_capex_discipline | B319: 575 | C319: 68.958437 | D319: 69.754121 | E319: 7.8924423
A320: DL1_deleverage_mild | B320: 575 | C320: 69.036343 | D320: 69.94291 | E320: 7.8163312
A321: DL2_deleverage_moderate | B321: 575 | C321: 69.278171 | D321: 70.10155 | E321: 7.7335387
A322: MX1_cost_and_deleverage | B322: 575 | C322: 69.258592 | D322: 70.063044 | E322: 7.8858376
... A328: WC2_supplier_financing | B328: 575 | C328: 69.237714 | D328: 69.990417 | E328: 7.9262902
A331: 입력 4: frozen_outputs/final_freeze/stage6_multi_oracle_eval/summary_by_policy_beta.csv
A332: 파일 크기(bytes) | B332: 1528 | C332: 생산 코드 | D332: src/credit_recourse/rl/pipelines/final_stage6_candidate_iql_multi_oracle_eval/pipeline.py | E332: SHA256 | F332: 6D1EF59AA1AF4C038F2CBB7BF66904977F6F04E30F5E27D96D526C3282048597 | G332: 읽기 상태 | H332: OK
A333: policy | B333: count | C333: mean | D333: median | E333: std
A334: C0_noop | B334: 575 | C334: 64.894768 | D334: 64.531146 | E334: 6.1222818
A335: C2_weakest_component_rule | B335: 575 | C335: 65.029598 | D335: 64.738599 | E335: 6.1241321
A336: C3_candidate_iql | B336: 575 | C336: 64.970598 | D336: 64.702789 | E336: 6.1376975
A337: C3_candidate_iql_q_argmax | B337: 575 | C337: 64.947636 | D337: 64.596664 | E337: 6.14245
A338: C3_candidate_iql_q_rerank_at_3 | B338: 575 | C338: 64.968816 | D338: 64.638374 | E338: 6.1446215
A339: C3_candidate_iql_q_rerank_at_5 | B339: 575 | C339: 64.961284 | D339: 64.615607 | E339: 6.1446516
A340: C3_candidate_iql_q_rerank_at_7 | B340: 575 | C340: 64.953749 | D340: 64.596664 | E340: 6.1462098
A341: C3_candidate_iql_q_rerank_at_9 | B341: 575 | C341: 64.950795 | D341: 64.596664 | E341: 6.1460842
A342: CX1_capex_discipline | B342: 575 | C342: 64.907527 | D342: 64.539142 | E342: 6.1207303
A343: DL1_deleverage_mild | B343: 575 | C343: 64.919771 | D343: 64.540374 | E343: 6.1218675
A344: DL2_deleverage_moderate | B344: 575 | C344: 64.938757 | D344: 64.55202 | E344: 6.122026
A345: MX1_cost_and_deleverage | B345: 575 | C345: 65.003835 | D345: 64.639422 | E345: 6.1244942
... A351: WC2_supplier_financing | B351: 575 | C351: 64.880736 | D351: 64.529951 | E351: 6.1194563
A354: 입력 5: frozen_outputs/final_freeze/stage6_multi_oracle_eval/summary_by_policy_gamma.csv
A355: 파일 크기(bytes) | B355: 1533 | C355: 생산 코드 | D355: src/credit_recourse/rl/pipelines/final_stage6_candidate_iql_multi_oracle_eval/pipeline.py | E355: SHA256 | F355: 7A62D5E0CDE36ACD28F22545997D7EFCD80C653A85C4F722C21DA7A160AE03DB | G355: 읽기 상태 | H355: OK
A356: policy | B356: count | C356: mean | D356: median | E356: std
A357: C0_noop | B357: 575 | C357: 67.346393 | D357: 67.216071 | E357: 6.8693102
A358: C2_weakest_component_rule | B358: 575 | C358: 67.748135 | D358: 67.554735 | E358: 6.8584342
A359: C3_candidate_iql | B359: 575 | C359: 67.941173 | D359: 67.737441 | E359: 6.8406838
A360: C3_candidate_iql_q_argmax | B360: 575 | C360: 67.766615 | D360: 67.554735 | E360: 6.8333222
A361: C3_candidate_iql_q_rerank_at_3 | B361: 575 | C361: 67.89419 | D361: 67.554735 | E361: 6.7822537
A362: C3_candidate_iql_q_rerank_at_5 | B362: 575 | C362: 67.835207 | D362: 67.541608 | E362: 6.807105
A363: C3_candidate_iql_q_rerank_at_7 | B363: 575 | C363: 67.788883 | D363: 67.525167 | E363: 6.8186435
A364: C3_candidate_iql_q_rerank_at_9 | B364: 575 | C364: 67.779309 | D364: 67.541608 | E364: 6.8272155
A365: CX1_capex_discipline | B365: 575 | C365: 67.532803 | D365: 67.360485 | E365: 6.8114036
A366: DL1_deleverage_mild | B366: 575 | C366: 67.69043 | D366: 67.426369 | E366: 6.7816859
A367: DL2_deleverage_moderate | B367: 575 | C367: 67.930428 | D367: 67.685705 | E367: 6.6935825
A368: MX1_cost_and_deleverage | B368: 575 | C368: 67.785245 | D368: 67.678353 | E368: 6.7736336
... A374: WC2_supplier_financing | B374: 575 | C374: 67.762752 | D374: 67.519333 | E374: 6.8556236
A377: 입력 6: frozen_outputs/final_freeze/stage6_multi_oracle_eval/final_policy_summary.csv
A378: 파일 크기(bytes) | B378: 4624 | C378: 생산 코드 | D378: src/credit_recourse/rl/pipelines/final_stage6_candidate_iql_multi_oracle_eval/pipeline.py | E378: SHA256 | F378: 9633B03DCF8A75375371A96B8C930DDBE5FDA744BE3998FAEE3235481727172B | G378: 읽기 상태 | H378: OK
A379: policy | B379: n | C379: headline_policy | D379: headline_policy_reason | E379: mean_R_score_alpha | F379: mean_delta_R_score_alpha | G379: median_delta_R_score_alpha | H379: positive_share_delta_R_score_alpha | I379: mean_R_score_beta | J379: mean_delta_R_score_beta | K379: median_delta_R_score_beta | L379: positive_share_delta_R_score_beta | M379: mean_R_score_gamma | N379: mean_delta_R_score_gamma | O379: median_delta_R_score_gamma | P379: positive_share_delta_R_score_gamma
A380: C0_noop | B380: 575 | C380: False | E380: 68.758255 | F380: 0 | G380: 0 | H380: 0 | I380: 64.894768 | J380: 0 | K380: 0 | L380: 0 | M380: 67.346393 | N380: 0 | O380: 0 | P380: 0
A381: C2_weakest_component_rule | B381: 575 | C381: False | E381: 69.26387 | F381: 0.50561586 | G381: 0.14214537 | H381: 0.54782609 | I381: 65.029598 | J381: 0.13483053 | K381: 0.12601525 | L381: 0.94434783 | M381: 67.748135 | N381: 0.40174213 | O381: 0.08309367 | P381: 0.53043478
A382: C3_candidate_iql | B382: 575 | C382: False | E382: 69.388567 | F382: 0.63031255 | G382: 0.14214537 | H382: 0.50782609 | I382: 64.970598 | J382: 0.07583031 | K382: 0.038370021 | L382: 0.83130435 | M382: 67.941173 | N382: 0.59478066 | O382: 0.23526326 | P382: 0.57043478
A383: C3_candidate_iql_q_argmax | B383: 575 | C383: False | E383: 69.249294 | F383: 0.49103939 | G383: 0 | H383: 0.48 | I383: 64.947636 | J383: 0.052867882 | K383: 0.024252622 | L383: 0.86956522 | M383: 67.766615 | N383: 0.42022202 | O383: 0 | P383: 0.48521739
A384: C3_candidate_iql_q_rerank_at_3 | B384: 575 | C384: False | E384: 69.351192 | F384: 0.59293687 | G384: 0.14214537 | H384: 0.52869565 | I384: 64.968816 | J384: 0.074047808 | K384: 0.038253043 | L384: 0.88173913 | M384: 67.89419 | N384: 0.54779722 | O384: 0.20470528 | P384: 0.57217391
A385: C3_candidate_iql_q_rerank_at_5 | B385: 575 | C385: False | E385: 69.302726 | F385: 0.54447179 | G385: 0.14214537 | H385: 0.51478261 | I385: 64.961284 | J385: 0.066516573 | K385: 0.03034302 | L385: 0.88 | M385: 67.835207 | N385: 0.48881421 | O385: 0.12909112 | P385: 0.52695652
A386: C3_candidate_iql_q_rerank_at_7 | B386: 575 | C386: False | E386: 69.270506 | F386: 0.51225163 | G386: 0 | H386: 0.49391304 | I386: 64.953749 | J386: 0.058981569 | K386: 0.02800733 | L386: 0.85391304 | M386: 67.788883 | N386: 0.44249055 | O386: 0 | P386: 0.4973913
A387: C3_candidate_iql_q_rerank_at_9 | B387: 575 | C387: False | E387: 69.268194 | F387: 0.50993899 | G387: 0 | H387: 0.49043478 | I387: 64.950795 | J387: 0.056027384 | K387: 0.026682354 | L387: 0.85391304 | M387: 67.779309 | N387: 0.43291666 | O387: 0 | P387: 0.49391304
A388: CX1_capex_discipline | B388: 575 | C388: False | E388: 68.958437 | F388: 0.20018234 | G388: 0 | H388: 0.3026087 | I388: 64.907527 | J388: 0.01275863 | K388: 0.0088786659 | L388: 1 | M388: 67.532803 | N388: 0.18641058 | O388: 0 | P388: 0.29913043
A389: DL1_deleverage_mild | B389: 575 | C389: False | E389: 69.036343 | F389: 0.27808795 | G389: 0 | H389: 0.23652174 | I389: 64.919771 | J389: 0.025003004 | K389: 0.015160503 | L389: 0.71478261 | M389: 67.69043 | N389: 0.34403744 | O389: 0 | P389: 0.46608696
A390: DL2_deleverage_moderate | B390: 575 | C390: False | E390: 69.278171 | F390: 0.51991642 | G390: 0 | H390: 0.34782609 | I390: 64.938757 | J390: 0.043989511 | K390: 0.026249004 | L390: 0.71304348 | M390: 67.930428 | N390: 0.58403571 | O390: 0.1629485 | P390: 0.54086957
A391: MX1_cost_and_deleverage | B391: 575 | C391: False | E391: 69.258592 | F391: 0.50033695 | G391: 0.14214537 | H391: 0.52869565 | I391: 65.003835 | J391: 0.1090671 | K391: 0.099404208 | L391: 0.99652174 | M391: 67.785245 | N391: 0.43885222 | O391: 0.087135813 | P391: 0.53391304
... A397: WC2_supplier_financing | B397: 575 | C397: False | E397: 69.237714 | F397: 0.479459 | G397: 0.34923652 | H397: 0.55130435 | I397: 64.880736 | J397: -0.014031488 | K397: -0.0037376368 | L397: 0.43478261 | M397: 67.762752 | N397: 0.41635917 | O397: 0.20715325 | P397: 0.59652174
A400: 입력 7: frozen_outputs/final_freeze/stage6_candidate_selector_eval/derived_comparators_runtime.json
A401: 파일 크기(bytes) | B401: 11880 | C401: 생산 코드 | D401: src/credit_recourse/rl/pipelines/final_stage6_candidate_iql_multi_oracle_eval/pipeline.py | E401: SHA256 | F401: DF0D513C49B6AD23008452379132245622350DE182E9BC52FB9196B239865844 | G401: 읽기 상태 | H401: OK
...

Sheet CHART_DATA
A1: F4 · 그림 데이터
A2: 실제 실행 산출물과 연결된 데이터입니다. 차트는 이 시트의 값을 참조하므로 Excel에서 직접 편집할 수 있습니다.
A4: policy | B4: mean_delta_R_score_alpha | C4: mean_delta_R_score_beta | D4: mean_delta_R_score_gamma
A5: ='SOURCE'!A380 | B5: ='SOURCE'!F380 | C5: ='SOURCE'!J380 | D5: ='SOURCE'!N380
A6: ='SOURCE'!A381 | B6: ='SOURCE'!F381 | C6: ='SOURCE'!J381 | D6: ='SOURCE'!N381
A7: ='SOURCE'!A382 | B7: ='SOURCE'!F382 | C7: ='SOURCE'!J382 | D7: ='SOURCE'!N382
A8: ='SOURCE'!A383 | B8: ='SOURCE'!F383 | C8: ='SOURCE'!J383 | D8: ='SOURCE'!N383
A9: ='SOURCE'!A384 | B9: ='SOURCE'!F384 | C9: ='SOURCE'!J384 | D9: ='SOURCE'!N384
A10: ='SOURCE'!A385 | B10: ='SOURCE'!F385 | C10: ='SOURCE'!J385 | D10: ='SOURCE'!N385
A11: ='SOURCE'!A386 | B11: ='SOURCE'!F386 | C11: ='SOURCE'!J386 | D11: ='SOURCE'!N386
A12: ='SOURCE'!A387 | B12: ='SOURCE'!F387 | C12: ='SOURCE'!J387 | D12: ='SOURCE'!N387
A13: ='SOURCE'!A388 | B13: ='SOURCE'!F388 | C13: ='SOURCE'!J388 | D13: ='SOURCE'!N388
A14: ='SOURCE'!A389 | B14: ='SOURCE'!F389 | C14: ='SOURCE'!J389 | D14: ='SOURCE'!N389
A15: ='SOURCE'!A390 | B15: ='SOURCE'!F390 | C15: ='SOURCE'!J390 | D15: ='SOURCE'!N390
A16: ='SOURCE'!A391 | B16: ='SOURCE'!F391 | C16: ='SOURCE'!J391 | D16: ='SOURCE'!N391
... A22: ='SOURCE'!A397 | B22: ='SOURCE'!F397 | C22: ='SOURCE'!J397 | D22: ='SOURCE'!N397

Sheet CHART
A1: F4 · 그림 4. Oracle별 표준행동 선호 양상
A2: CHART_DATA를 참조하는 편집 가능한 Excel 차트입니다.
