Workbook

Sheet README
A1: F10 · 그림 10. 같은 C4에서 나뉜 자기 재검토와 외부 정책 참조 후 수정
A2: 논문 인쇄값을 계산 입력으로 쓰지 않고, 선택 실행의 실제 산출물에서 값을 계산한 Excel입니다.
A4: 항목 | B4: 내용
A5: 선택 실행 | B5: V11_FINAL_FROZEN_REPLAY_RESUME
A6: 실행 방식 | B6: FrozenReplay
A7: 논문 항목 읽기 | B7: 논문 DOCX에서 번호·제목·위치만 동적으로 읽음
A8: 논문 위치 | B8: 6.4 자기 재검토와 외부 정책 참조의 효과 구분 · 인쇄면 75
A9: 관측·집계 단위 | B9: cohort_id + budget_label + contrast
A10: 선택 조건 | B10: [[{"column": "oracle_backend", "op": "equals", "value": "alpha"}, {"column": "contrast", "op": "in", "values": ["self_revision", "reference_content_conditional", "reference_plus_revision_package"]}]]
A11: 계산 방법 | B11: 계산 가능한 결과는 실행 산출물에서 계산하고 정의·설정은 별도로 구분
A12: 생산 코드 | B12: Stage7 branch implementation and matched analysis
A13: 실제 입력 산출물 | B13: src/credit_recourse/rl/pipelines/final_stage7_llm_action_generation/pipeline.py embedded://selected-run-output/data/analysis/paper_repro/05_extension_e3_e4/e3_c4r_journal/v3_matched/c4r_matched_v3_contrasts.csv

Sheet SOURCE
A1: F10 · 실제 입력 산출물
A2: 선택 실행에서 읽은 실제 중간·최종 산출물입니다. 아래 ANALYSIS가 이 셀들을 직접 참조합니다.
A4: 입력 1: src/credit_recourse/rl/pipelines/final_stage7_llm_action_generation/pipeline.py
A5: 파일 크기(bytes) | B5: 75234 | C5: 생산 코드 | D5: Stage7 branch implementation and matched analysis | E5: SHA256 | F5: C87934E9DCC5CB1A3A05F7299F13DD2A0956FB47EEE03448A3727C99BA2CECFC | G5: 읽기 상태 | H5: OK
A6: line_number | B6: text
A7: 1 | B7: from __future__ import annotations
A8: 2
A9: 3 | B9: """Stage 7 — LLM Recourse Action Generation.
A10: 4
A11: 5 | B11: Reads the Stage 2 ``phase_eval_candidate`` serving panel (state-only) and the
A12: 6 | B12: Stage 6 ``policy_actions.parquet`` (for the RL reference policy on
A13: 7 | B13: reference conditions C6/C6X/C7/C8), runs the configured LLM backend across
A14: 8 | B14: conditions × modes, and emits a Stage 6-compatible action table that
A15: 9 | B15: Stage 8 will score with the Stage 6 simulator + Oracle substrate.
A16: 10
A17: 11 | B17: The stage is deliberately narrow:
A18: 12
A19: 13 | B19: * It does **not** simulate, score, or evaluate. Stage 8 does that.
A20: 14 | B20: * It does **not** redefine the Oracle, the simulator, the candidate library,
A21: 15 | B21: the temporal split, or the RL winner (per the Stage 7-9 LLM contract §1).
A22: 16 | B22: * It records every prompt, every raw LLM response, every parsed action, and
A23: 17 | B23: every failure category so a reviewer can audit any specific LLM decision
A24: 18 | B24: end to end.
A25: 19
A26: 20 | B26: Outputs (under ``data/final_freeze/stage7_llm_action_generation/``):
A27: 21
A28: 22 | B28: * ``llm_stage7_action_table.parquet`` — Stage 6 policy_actions-compatible
A29: 23 | B29: schema (row_id, policy, candidate_id, action__* columns, plus Stage 7
A30: 24 | B30: diagnostics).
A31: 25 | B31: * ``llm_stage7_prompt_manifest.json`` — frozen prompts, backend identity,
A32: 26 | B32: reproducibility metadata.
A33: 27 | B33: * ``llm_stage7_failure_audit.csv`` — per-row failure taxonomy classification.
A34: 28 | B34: * ``llm_stage7_response_log.parquet`` — raw response text per request for
A35: 29 | B35: full traceability.
A36: 30 | B36: * ``metadata.json`` — stage status, hashes, backend identity, condition
A37: 31 | B37: matrix used.
A38: 32 | B38: """
A39: 33
A40: 34 | B40: import argparse
A41: 35 | B41: import hashlib
A42: 36 | B42: import json
A43: 37 | B43: import sys
A44: 38 | B44: import threading
A45: 39 | B45: import time
A46: 40 | B46: from concurrent.futures import ThreadPoolExecutor, as_completed
A47: 41 | B47: from dataclasses import asdict
A48: 42 | B48: from datetime import datetime, timezone
A49: 43 | B49: from pathlib import Path
A50: 44
A51: 45 | B51: import pandas as pd
A52: 46
A53: 47 | B53: from credit_recourse.contracts.stage_paths import stage_dir, final_root
A54: 48 | B54: from credit_recourse.rl.common.actions import (
A55: 49 | B55: active_config_hashes,
A56: 50 | B56: assert_hashes_match,
A57: 51 | B57: load_action_space,
A58: 52 | B58: resolve_candidate_library_path,
A59: 53 | B59: )
A60: 54 | B60: from credit_recourse.rl.common.io import read_parquet_required, write_json
A61: 55
A62: 56 | B62: from .llm_backends import LLMBackend, LLMRequest, LLMResponse, LiveLLMBackend, make_backend
A63: 57 | B63: from .budget_contract import (
A64: 58 | B64: BUDGET_AUDIT_COLUMNS,
A65: 59 | B65: ACTION_BUDGET_CONTRACT_SCHEMA_VERSION,
A66: 60 | B66: action_l1,
A67: 61 | B67: budget_applies,
A68: 62 | B68: disabled_budget_contract,
A69: 63 | B69: make_action_budget_contract,
A70: 64 | B70: )
A71: 65 | B71: from .prompt_builder import (
A72: 66 | B72: ICC_PROBE_SCHEMA_VERSION,
A73: 67 | B73: ICC_PROBE_TARGET_FEATURE,
... A84: 78 | B84: )
A85: 79
A86: 80
A87: 81 | B87: def _now() -> str:
A88: 82 | B88: return datetime.now(timezone.utc).isoformat()
A89: 83
A90: 84
A91: 85 | B91: def _sha256_bytes(data: bytes) -> str:
A92: 86 | B92: return hashlib.sha256(data).hexdigest()
A93: 87
A94: 88
A95: 89 | B95: STAGE7_CHECKPOINT_SCHEMA_VERSION = "stage7_llm_request_checkpoint_v1"
A96: 90 | B96: STAGE7_PROMPT_PAYLOAD_ARCHIVE_SCHEMA_VERSION = "stage7_prompt_payload_archive_v1"
A97: 91 | B97: DEFAULT_STAGE7_CHECKPOINT_NAME = "llm_stage7_response_checkpoint.jsonl"
A98: 92
A99: 93 | B99: # 2026-07-04 contract addendum (LLM789-008/009): IC-c exposes the firm NAME
A100: 94 | B100: # (research decision superseding-in-part contract v4 §6.1 identifier-only
A101: 95 | B101: # list) and the optional IC-c prior-knowledge probe emits the contract-v4
A102: 96 | B102: # icc_probe_* columns. Runs carrying this key are verified against the
A103: 97 | B103: # addendum; legacy runs without it receive warnings only.
A104: 98 | B104: STAGE7_CONTRACT_ADDENDUM = "20260704_icc_firm_name_probe_v1"
A105: 99 | B105: ICC_PROBE_CHECKPOINT_NAME = "llm_stage7_icc_probe_checkpoint.jsonl"
A106: 100 | B106: ICC_PROBE_COLUMNS = [
A107: 101 | B107: "icc_probe_response_raw", "icc_probe_value", "icc_contamination_flag",
A108: 102 | B108: "icc_probe_parse_error", "icc_probe_rel_err", "icc_probe_panel_value",
A109: 103 | B109: ]
A110: 104
A111: 105
...

Sheet CHART_DATA
A1: F10 · 그림 데이터
A2: 실제 실행 산출물과 연결된 데이터입니다. 차트는 이 시트의 값을 참조하므로 Excel에서 직접 편집할 수 있습니다.
A4: cohort_id × budget_label × contrast | B4: mean_increment
A5: ='SOURCE'!A1708&" | "&'SOURCE'!D1708&" | "&'SOURCE'!G1708 | B5: ='SOURCE'!I1708
A6: ='SOURCE'!A1709&" | "&'SOURCE'!D1709&" | "&'SOURCE'!G1709 | B6: ='SOURCE'!I1709
A7: ='SOURCE'!A1710&" | "&'SOURCE'!D1710&" | "&'SOURCE'!G1710 | B7: ='SOURCE'!I1710
A8: ='SOURCE'!A1711&" | "&'SOURCE'!D1711&" | "&'SOURCE'!G1711 | B8: ='SOURCE'!I1711
A9: ='SOURCE'!A1720&" | "&'SOURCE'!D1720&" | "&'SOURCE'!G1720 | B9: ='SOURCE'!I1720
A10: ='SOURCE'!A1721&" | "&'SOURCE'!D1721&" | "&'SOURCE'!G1721 | B10: ='SOURCE'!I1721
A11: ='SOURCE'!A1722&" | "&'SOURCE'!D1722&" | "&'SOURCE'!G1722 | B11: ='SOURCE'!I1722
A12: ='SOURCE'!A1723&" | "&'SOURCE'!D1723&" | "&'SOURCE'!G1723 | B12: ='SOURCE'!I1723
A13: ='SOURCE'!A1732&" | "&'SOURCE'!D1732&" | "&'SOURCE'!G1732 | B13: ='SOURCE'!I1732
A14: ='SOURCE'!A1733&" | "&'SOURCE'!D1733&" | "&'SOURCE'!G1733 | B14: ='SOURCE'!I1733
A15: ='SOURCE'!A1734&" | "&'SOURCE'!D1734&" | "&'SOURCE'!G1734 | B15: ='SOURCE'!I1734
A16: ='SOURCE'!A1735&" | "&'SOURCE'!D1735&" | "&'SOURCE'!G1735 | B16: ='SOURCE'!I1735
A17: ='SOURCE'!A1744&" | "&'SOURCE'!D1744&" | "&'SOURCE'!G1744 | B17: ='SOURCE'!I1744
A18: ='SOURCE'!A1745&" | "&'SOURCE'!D1745&" | "&'SOURCE'!G1745 | B18: ='SOURCE'!I1745
A19: ='SOURCE'!A1746&" | "&'SOURCE'!D1746&" | "&'SOURCE'!G1746 | B19: ='SOURCE'!I1746
A20: ='SOURCE'!A1747&" | "&'SOURCE'!D1747&" | "&'SOURCE'!G1747 | B20: ='SOURCE'!I1747
A21: ='SOURCE'!A1756&" | "&'SOURCE'!D1756&" | "&'SOURCE'!G1756 | B21: ='SOURCE'!I1756
A22: ='SOURCE'!A1757&" | "&'SOURCE'!D1757&" | "&'SOURCE'!G1757 | B22: ='SOURCE'!I1757
A23: ='SOURCE'!A1758&" | "&'SOURCE'!D1758&" | "&'SOURCE'!G1758 | B23: ='SOURCE'!I1758
A24: ='SOURCE'!A1759&" | "&'SOURCE'!D1759&" | "&'SOURCE'!G1759 | B24: ='SOURCE'!I1759
A25: ='SOURCE'!A1768&" | "&'SOURCE'!D1768&" | "&'SOURCE'!G1768 | B25: ='SOURCE'!I1768
A26: ='SOURCE'!A1769&" | "&'SOURCE'!D1769&" | "&'SOURCE'!G1769 | B26: ='SOURCE'!I1769
A27: ='SOURCE'!A1770&" | "&'SOURCE'!D1770&" | "&'SOURCE'!G1770 | B27: ='SOURCE'!I1770
A28: ='SOURCE'!A1771&" | "&'SOURCE'!D1771&" | "&'SOURCE'!G1771 | B28: ='SOURCE'!I1771

Sheet CHART
A1: F10 · 그림 10. 같은 C4에서 나뉜 자기 재검토와 외부 정책 참조 후 수정
A2: CHART_DATA를 참조하는 편집 가능한 Excel 차트입니다.
